{
"meta":{"test_sets":[],"test_metrics":[],"learn_metrics":[{"best_value":"Min","name":"Logloss"}],"launch_mode":"Train","parameters":"","iteration_count":1000,"learn_sets":["learn"],"name":"experiment"},
"iterations":[
{"learn":[0.6849312415],"iteration":0,"passed_time":0.05921972419,"remaining_time":59.16050446},
{"learn":[0.6772024448],"iteration":1,"passed_time":0.07768338453,"remaining_time":38.76400888},
{"learn":[0.6692120479],"iteration":2,"passed_time":0.0825122332,"remaining_time":27.4215655},
{"learn":[0.6609950432],"iteration":3,"passed_time":0.09635448458,"remaining_time":23.99226666},
{"learn":[0.6518372756],"iteration":4,"passed_time":0.09780972219,"remaining_time":19.46413472},
{"learn":[0.644618988],"iteration":5,"passed_time":0.09912067087,"remaining_time":16.42099114},
{"learn":[0.6357980875],"iteration":6,"passed_time":0.1013021344,"remaining_time":14.37043135},
{"learn":[0.6272003467],"iteration":7,"passed_time":0.1165892324,"remaining_time":14.45706482},
{"learn":[0.6196198097],"iteration":8,"passed_time":0.1179623166,"remaining_time":12.98896175},
{"learn":[0.6116510538],"iteration":9,"passed_time":0.1189099603,"remaining_time":11.77208607},
{"learn":[0.6044938014],"iteration":10,"passed_time":0.1200324563,"remaining_time":10.79200903},
{"learn":[0.5966194226],"iteration":11,"passed_time":0.1213955941,"remaining_time":9.994903911},
{"learn":[0.5890919245],"iteration":12,"passed_time":0.123240932,"remaining_time":9.356830763},
{"learn":[0.580991745],"iteration":13,"passed_time":0.1243979072,"remaining_time":8.761166895},
{"learn":[0.5740273182],"iteration":14,"passed_time":0.1301725034,"remaining_time":8.547994392},
{"learn":[0.5653285247],"iteration":15,"passed_time":0.1314446901,"remaining_time":8.083848444},
{"learn":[0.5584830504],"iteration":16,"passed_time":0.1323914864,"remaining_time":7.655343008},
{"learn":[0.5530366164],"iteration":17,"passed_time":0.1334636162,"remaining_time":7.281181729},
{"learn":[0.5465104763],"iteration":18,"passed_time":0.1412663632,"remaining_time":7.293805385},
{"learn":[0.5395343487],"iteration":19,"passed_time":0.1447560786,"remaining_time":7.093047853},
{"learn":[0.5336242823],"iteration":20,"passed_time":0.1501377962,"remaining_time":6.99928107},
{"learn":[0.5269536605],"iteration":21,"passed_time":0.1512871977,"remaining_time":6.725403607},
{"learn":[0.5224266786],"iteration":22,"passed_time":0.1554508362,"remaining_time":6.603281171},
{"learn":[0.5166021494],"iteration":23,"passed_time":0.156704287,"remaining_time":6.372641003},
{"learn":[0.5109120516],"iteration":24,"passed_time":0.1587939289,"remaining_time":6.192963229},
{"learn":[0.5048745962],"iteration":25,"passed_time":0.1601066332,"remaining_time":5.997840797},
{"learn":[0.4989238886],"iteration":26,"passed_time":0.163592987,"remaining_time":5.895406532},
{"learn":[0.4932793837],"iteration":27,"passed_time":0.1652443753,"remaining_time":5.736340455},
{"learn":[0.4880459125],"iteration":28,"passed_time":0.1668074709,"remaining_time":5.585174286},
{"learn":[0.4817676544],"iteration":29,"passed_time":0.1707185141,"remaining_time":5.519898622},
{"learn":[0.4752735725],"iteration":30,"passed_time":0.1719603652,"remaining_time":5.375148189},
{"learn":[0.470424432],"iteration":31,"passed_time":0.1731285859,"remaining_time":5.237139724},
{"learn":[0.4658253376],"iteration":32,"passed_time":0.1742790745,"remaining_time":5.106905001},
{"learn":[0.4608385379],"iteration":33,"passed_time":0.1763828199,"remaining_time":5.011347178},
{"learn":[0.455885557],"iteration":34,"passed_time":0.1775233204,"remaining_time":4.894571548},
{"learn":[0.4500369292],"iteration":35,"passed_time":0.1787727332,"remaining_time":4.787136524},
{"learn":[0.4456577301],"iteration":36,"passed_time":0.1798984822,"remaining_time":4.682222658},
{"learn":[0.4418957784],"iteration":37,"passed_time":0.181573568,"remaining_time":4.596678222},
{"learn":[0.4367303848],"iteration":38,"passed_time":0.1829517676,"remaining_time":4.508119196},
{"learn":[0.4319243798],"iteration":39,"passed_time":0.1845758418,"remaining_time":4.429820202},
{"learn":[0.4275154701],"iteration":40,"passed_time":0.1861514133,"remaining_time":4.35412696},
{"learn":[0.4230296062],"iteration":41,"passed_time":0.190797861,"remaining_time":4.352008353},
{"learn":[0.4185573871],"iteration":42,"passed_time":0.1917946707,"remaining_time":4.268546509},
{"learn":[0.4142819551],"iteration":43,"passed_time":0.1926439661,"remaining_time":4.18562799},
{"learn":[0.4102294628],"iteration":44,"passed_time":0.1939267495,"remaining_time":4.115556573},
{"learn":[0.4063413327],"iteration":45,"passed_time":0.2003739793,"remaining_time":4.155582093},
{"learn":[0.4033642182],"iteration":46,"passed_time":0.207312733,"remaining_time":4.20359648},
{"learn":[0.3995457062],"iteration":47,"passed_time":0.2111301808,"remaining_time":4.187415252},
{"learn":[0.3952903014],"iteration":48,"passed_time":0.2132502938,"remaining_time":4.138796518},
{"learn":[0.391574016],"iteration":49,"passed_time":0.2151774541,"remaining_time":4.088371627},
{"learn":[0.3873310823],"iteration":50,"passed_time":0.2162943868,"remaining_time":4.024772021},
{"learn":[0.3838449625],"iteration":51,"passed_time":0.2177901966,"remaining_time":3.970482816},
{"learn":[0.3796955989],"iteration":52,"passed_time":0.2194563215,"remaining_time":3.92122899},
{"learn":[0.3761530656],"iteration":53,"passed_time":0.2221413752,"remaining_time":3.891587796},
{"learn":[0.3731957216],"iteration":54,"passed_time":0.2236401762,"remaining_time":3.842544845},
{"learn":[0.3700717779],"iteration":55,"passed_time":0.2247750092,"remaining_time":3.789064441},
{"learn":[0.3668209956],"iteration":56,"passed_time":0.225638863,"remaining_time":3.732937681},
{"learn":[0.3638739586],"iteration":57,"passed_time":0.2276435119,"remaining_time":3.697244624},
{"learn":[0.3607578278],"iteration":58,"passed_time":0.2287544937,"remaining_time":3.648440315},
{"learn":[0.357205501],"iteration":59,"passed_time":0.2300663866,"remaining_time":3.60437339},
{"learn":[0.3541562007],"iteration":60,"passed_time":0.2311426027,"remaining_time":3.558080392},
{"learn":[0.3510775566],"iteration":61,"passed_time":0.2363929606,"remaining_time":3.576396727},
{"learn":[0.3485911809],"iteration":62,"passed_time":0.2375584351,"remaining_time":3.533210376},
{"learn":[0.3459683565],"iteration":63,"passed_time":0.2386819519,"remaining_time":3.490723547},
{"learn":[0.3432879815],"iteration":64,"passed_time":0.2398696102,"remaining_time":3.450432085},
{"learn":[0.3404010626],"iteration":65,"passed_time":0.2426443594,"remaining_time":3.433785328},
{"learn":[0.3373699188],"iteration":66,"passed_time":0.2438796721,"remaining_time":3.396115434},
{"learn":[0.3348313845],"iteration":67,"passed_time":0.2512180188,"remaining_time":3.44316461},
{"learn":[0.3319111237],"iteration":68,"passed_time":0.2522971627,"remaining_time":3.404183457},
{"learn":[0.3306815074],"iteration":69,"passed_time":0.255280493,"remaining_time":3.391583693},
{"learn":[0.3277719571],"iteration":70,"passed_time":0.256421954,"remaining_time":3.355154863},
{"learn":[0.3242729627],"iteration":71,"passed_time":0.2574077853,"remaining_time":3.317700344},
{"learn":[0.3216841771],"iteration":72,"passed_time":0.2585028036,"remaining_time":3.282631492},
{"learn":[0.3188315905],"iteration":73,"passed_time":0.2613246574,"remaining_time":3.270089631},
{"learn":[0.3161295744],"iteration":74,"passed_time":0.2632604233,"remaining_time":3.246878554},
{"learn":[0.31317113],"iteration":75,"passed_time":0.2650698632,"remaining_time":3.222691494},
{"learn":[0.3109546075],"iteration":76,"passed_time":0.267135257,"remaining_time":3.202153795},
{"learn":[0.3086519241],"iteration":77,"passed_time":0.2687567211,"remaining_time":3.176842267},
{"learn":[0.3061940853],"iteration":78,"passed_time":0.2699013235,"remaining_time":3.146571125},
{"learn":[0.3035562222],"iteration":79,"passed_time":0.2711691523,"remaining_time":3.118445251},
{"learn":[0.3013373522],"iteration":80,"passed_time":0.2723736019,"remaining_time":3.090263458},
{"learn":[0.2990546043],"iteration":81,"passed_time":0.2753817041,"remaining_time":3.082931761},
{"learn":[0.2968612084],"iteration":82,"passed_time":0.2768656308,"remaining_time":3.05886486},
{"learn":[0.2942064175],"iteration":83,"passed_time":0.2794249778,"remaining_time":3.047062853},
{"learn":[0.291704563],"iteration":84,"passed_time":0.2825582439,"remaining_time":3.041656391},
{"learn":[0.2896299729],"iteration":85,"passed_time":0.2884978449,"remaining_time":3.066128259},
{"learn":[0.2873911858],"iteration":86,"passed_time":0.2898846307,"remaining_time":3.042122619},
{"learn":[0.2850591586],"iteration":87,"passed_time":0.2909122248,"remaining_time":3.014908511},
{"learn":[0.282477764],"iteration":88,"passed_time":0.2975288217,"remaining_time":3.045491647},
{"learn":[0.2800233731],"iteration":89,"passed_time":0.2985651263,"remaining_time":3.018825166},
{"learn":[0.2777390847],"iteration":90,"passed_time":0.2997220888,"remaining_time":2.993927239},
{"learn":[0.2755842759],"iteration":91,"passed_time":0.3035265801,"remaining_time":2.995675377},
{"learn":[0.273351706],"iteration":92,"passed_time":0.3044377502,"remaining_time":2.969086445},
{"learn":[0.2711566228],"iteration":93,"passed_time":0.3056001592,"remaining_time":2.945465364},
{"learn":[0.2690904691],"iteration":94,"passed_time":0.3075195732,"remaining_time":2.929528565},
{"learn":[0.2671633134],"iteration":95,"passed_time":0.3101523165,"remaining_time":2.92060098},
{"learn":[0.2650833863],"iteration":96,"passed_time":0.3115315893,"remaining_time":2.90013428},
{"learn":[0.2624919598],"iteration":97,"passed_time":0.3132383292,"remaining_time":2.883071153},
{"learn":[0.2604404229],"iteration":98,"passed_time":0.32019142,"remaining_time":2.914065348},
{"learn":[0.258760489],"iteration":99,"passed_time":0.3220661777,"remaining_time":2.898595599},
{"learn":[0.2566678341],"iteration":100,"passed_time":0.3245773732,"remaining_time":2.889059985},
{"learn":[0.2545453218],"iteration":101,"passed_time":0.3258093976,"remaining_time":2.868400383},
{"learn":[0.2527360916],"iteration":102,"passed_time":0.326842328,"remaining_time":2.846384157},
{"learn":[0.2513885131],"iteration":103,"passed_time":0.3310860436,"remaining_time":2.852433606},
{"learn":[0.2492945378],"iteration":104,"passed_time":0.3323175048,"remaining_time":2.832611112},
{"learn":[0.2480216577],"iteration":105,"passed_time":0.3341434446,"remaining_time":2.818153203},
{"learn":[0.2457678868],"iteration":106,"passed_time":0.3353294921,"remaining_time":2.798590994},
{"learn":[0.2437765415],"iteration":107,"passed_time":0.3364859647,"remaining_time":2.779124819},
{"learn":[0.2416846202],"iteration":108,"passed_time":0.3376323126,"remaining_time":2.75991184},
{"learn":[0.2404528765],"iteration":109,"passed_time":0.3386548545,"remaining_time":2.740025641},
{"learn":[0.2390616123],"iteration":110,"passed_time":0.3398452055,"remaining_time":2.721823313},
{"learn":[0.237531662],"iteration":111,"passed_time":0.3410327648,"remaining_time":2.703902636},
{"learn":[0.2360803531],"iteration":112,"passed_time":0.3427452719,"remaining_time":2.690398727},
{"learn":[0.234607183],"iteration":113,"passed_time":0.3440242752,"remaining_time":2.673732525},
{"learn":[0.2332747166],"iteration":114,"passed_time":0.3451305732,"remaining_time":2.656004846},
{"learn":[0.2315119046],"iteration":115,"passed_time":0.3468430081,"remaining_time":2.643182923},
{"learn":[0.2300038154],"iteration":116,"passed_time":0.3488473965,"remaining_time":2.632754283},
{"learn":[0.2284390376],"iteration":117,"passed_time":0.3502039785,"remaining_time":2.617626348},
{"learn":[0.2267477329],"iteration":118,"passed_time":0.3516772068,"remaining_time":2.603593439},
{"learn":[0.225247108],"iteration":119,"passed_time":0.3536129832,"remaining_time":2.593161877},
{"learn":[0.223722788],"iteration":120,"passed_time":0.3559732019,"remaining_time":2.585954086},
{"learn":[0.2222637397],"iteration":121,"passed_time":0.3570351137,"remaining_time":2.569482212},
{"learn":[0.2210139311],"iteration":122,"passed_time":0.3580789838,"remaining_time":2.553132266},
{"learn":[0.21961247],"iteration":123,"passed_time":0.3590021959,"remaining_time":2.536176803},
{"learn":[0.2185743222],"iteration":124,"passed_time":0.3598894207,"remaining_time":2.519225945},
{"learn":[0.2171189785],"iteration":125,"passed_time":0.3611293156,"remaining_time":2.504976364},
{"learn":[0.2154717079],"iteration":126,"passed_time":0.3633948578,"remaining_time":2.497981975},
{"learn":[0.2141114015],"iteration":127,"passed_time":0.3646518737,"remaining_time":2.48419089},
{"learn":[0.2129172178],"iteration":128,"passed_time":0.3661306211,"remaining_time":2.472091248},
{"learn":[0.2114129433],"iteration":129,"passed_time":0.3675037577,"remaining_time":2.459448225},
{"learn":[0.2099696489],"iteration":130,"passed_time":0.3722503704,"remaining_time":2.46935551},
{"learn":[0.2084795145],"iteration":131,"passed_time":0.3737104227,"remaining_time":2.457429144},
{"learn":[0.2072166296],"iteration":132,"passed_time":0.3749050007,"remaining_time":2.443929591},
{"learn":[0.205712025],"iteration":133,"passed_time":0.376029824,"remaining_time":2.430162893},
{"learn":[0.2044506807],"iteration":134,"passed_time":0.3773184591,"remaining_time":2.41763309},
{"learn":[0.2033896079],"iteration":135,"passed_time":0.3784888751,"remaining_time":2.40451756},
{"learn":[0.2025711353],"iteration":136,"passed_time":0.3791585333,"remaining_time":2.388422002},
{"learn":[0.201324848],"iteration":137,"passed_time":0.3803990116,"remaining_time":2.376115565},
{"learn":[0.2002003926],"iteration":138,"passed_time":0.381640693,"remaining_time":2.363975804},
{"learn":[0.1987148065],"iteration":139,"passed_time":0.3873714394,"remaining_time":2.379567414},
{"learn":[0.1971743657],"iteration":140,"passed_time":0.3886139676,"remaining_time":2.367513462},
{"learn":[0.1957829182],"iteration":141,"passed_time":0.3901825916,"remaining_time":2.357582138},
{"learn":[0.1946373353],"iteration":142,"passed_time":0.3911575129,"remaining_time":2.34420971},
{"learn":[0.193380796],"iteration":143,"passed_time":0.3922834069,"remaining_time":2.331906919},
{"learn":[0.1923216673],"iteration":144,"passed_time":0.3933453983,"remaining_time":2.319381487},
{"learn":[0.1914067268],"iteration":145,"passed_time":0.3949358769,"remaining_time":2.310104376},
{"learn":[0.1904138785],"iteration":146,"passed_time":0.3964854963,"remaining_time":2.300694751},
{"learn":[0.1893297709],"iteration":147,"passed_time":0.3977068831,"remaining_time":2.289501787},
{"learn":[0.188093919],"iteration":148,"passed_time":0.3995470868,"remaining_time":2.281976986},
{"learn":[0.1870642809],"iteration":149,"passed_time":0.4006574927,"remaining_time":2.270392459},
{"learn":[0.1862275967],"iteration":150,"passed_time":0.4021244855,"remaining_time":2.260951578},
{"learn":[0.1852612495],"iteration":151,"passed_time":0.4035413332,"remaining_time":2.251335859},
{"learn":[0.1842821378],"iteration":152,"passed_time":0.4048049753,"remaining_time":2.240979177},
{"learn":[0.1833771376],"iteration":153,"passed_time":0.4064621563,"remaining_time":2.232902495},
{"learn":[0.1822209175],"iteration":154,"passed_time":0.4077991768,"remaining_time":2.223163254},
{"learn":[0.1813002366],"iteration":155,"passed_time":0.4097479871,"remaining_time":2.216841674},
{"learn":[0.1804706867],"iteration":156,"passed_time":0.4140303891,"remaining_time":2.223105847},
{"learn":[0.1794451567],"iteration":157,"passed_time":0.4152249388,"remaining_time":2.212781003},
{"learn":[0.178752349],"iteration":158,"passed_time":0.4165394782,"remaining_time":2.203205668},
{"learn":[0.1778820295],"iteration":159,"passed_time":0.4175515573,"remaining_time":2.192145676},
{"learn":[0.1766695059],"iteration":160,"passed_time":0.418585818,"remaining_time":2.181326095},
{"learn":[0.175857599],"iteration":161,"passed_time":0.4198011817,"remaining_time":2.171564138},
{"learn":[0.1747966913],"iteration":162,"passed_time":0.4221271731,"remaining_time":2.167610085},
{"learn":[0.1738825578],"iteration":163,"passed_time":0.4233583947,"remaining_time":2.158095231},
{"learn":[0.1730089371],"iteration":164,"passed_time":0.4245451988,"remaining_time":2.148456006},
{"learn":[0.172256433],"iteration":165,"passed_time":0.4306433484,"remaining_time":2.16359369},
{"learn":[0.1712080149],"iteration":166,"passed_time":0.4325815779,"remaining_time":2.157727272},
{"learn":[0.170377768],"iteration":167,"passed_time":0.4337489151,"remaining_time":2.148089865},
{"learn":[0.1695338396],"iteration":168,"passed_time":0.4349205852,"remaining_time":2.138574002},
{"learn":[0.168521551],"iteration":169,"passed_time":0.4359948966,"remaining_time":2.128680966},
{"learn":[0.1672407847],"iteration":170,"passed_time":0.4380625047,"remaining_time":2.123706529},
{"learn":[0.1663683745],"iteration":171,"passed_time":0.4397461969,"remaining_time":2.116917739},
{"learn":[0.1655134788],"iteration":172,"passed_time":0.4408921107,"remaining_time":2.1076172},
{"learn":[0.1645412628],"iteration":173,"passed_time":0.443130622,"remaining_time":2.103597091},
{"learn":[0.163606497],"iteration":174,"passed_time":0.4447875854,"remaining_time":2.09685576},
{"learn":[0.162597968],"iteration":175,"passed_time":0.4459526227,"remaining_time":2.087869097},
{"learn":[0.1617018626],"iteration":176,"passed_time":0.4473564607,"remaining_time":2.08008117},
{"learn":[0.1609658461],"iteration":177,"passed_time":0.4483506893,"remaining_time":2.070473408},
{"learn":[0.1602970637],"iteration":178,"passed_time":0.4506485936,"remaining_time":2.066941315},
{"learn":[0.1596933328],"iteration":179,"passed_time":0.4521268364,"remaining_time":2.059688922},
{"learn":[0.1587757697],"iteration":180,"passed_time":0.4531406834,"remaining_time":2.050399004},
{"learn":[0.158066071],"iteration":181,"passed_time":0.4541474716,"remaining_time":2.041168306},
{"learn":[0.1575503349],"iteration":182,"passed_time":0.4552672659,"remaining_time":2.032532001},
{"learn":[0.1568807639],"iteration":183,"passed_time":0.456576344,"remaining_time":2.02481683},
{"learn":[0.1562781517],"iteration":184,"passed_time":0.4587597849,"remaining_time":2.021022836},
{"learn":[0.1553823948],"iteration":185,"passed_time":0.459999139,"remaining_time":2.013114511},
{"learn":[0.1547340797],"iteration":186,"passed_time":0.4611411402,"remaining_time":2.004854262},
{"learn":[0.1541267725],"iteration":187,"passed_time":0.4627306916,"remaining_time":1.998602775},
{"learn":[0.1534749545],"iteration":188,"passed_time":0.464098335,"remaining_time":1.991448411},
{"learn":[0.1526125211],"iteration":189,"passed_time":0.4651278449,"remaining_time":1.982913444},
{"learn":[0.1517227063],"iteration":190,"passed_time":0.4661739003,"remaining_time":1.974527148},
{"learn":[0.1508102142],"iteration":191,"passed_time":0.4676365174,"remaining_time":1.967970344},
{"learn":[0.1501637789],"iteration":192,"passed_time":0.4687627485,"remaining_time":1.960059782},
{"learn":[0.1496881338],"iteration":193,"passed_time":0.4700241959,"remaining_time":1.952780938},
{"learn":[0.1490730139],"iteration":194,"passed_time":0.4721899798,"remaining_time":1.949297096},
{"learn":[0.1483916136],"iteration":195,"passed_time":0.4745254272,"remaining_time":1.946522671},
{"learn":[0.1476211181],"iteration":196,"passed_time":0.4760046069,"remaining_time":1.940262433},
{"learn":[0.1468306596],"iteration":197,"passed_time":0.47718886,"remaining_time":1.932855887},
{"learn":[0.1461650683],"iteration":198,"passed_time":0.4783792315,"remaining_time":1.925536505},
{"learn":[0.145557807],"iteration":199,"passed_time":0.4794908212,"remaining_time":1.917963285},
{"learn":[0.1448689241],"iteration":200,"passed_time":0.4806736282,"remaining_time":1.910737458},
{"learn":[0.1442427635],"iteration":201,"passed_time":0.4819379913,"remaining_time":1.903893649},
{"learn":[0.1434835012],"iteration":202,"passed_time":0.4831460387,"remaining_time":1.896883709},
{"learn":[0.1429464267],"iteration":203,"passed_time":0.4849874128,"remaining_time":1.892401866},
{"learn":[0.1422967085],"iteration":204,"passed_time":0.4859419554,"remaining_time":1.884506607},
{"learn":[0.1415137511],"iteration":205,"passed_time":0.486914838,"remaining_time":1.876749424},
{"learn":[0.1409215469],"iteration":206,"passed_time":0.4879662304,"remaining_time":1.869358554},
{"learn":[0.1403792821],"iteration":207,"passed_time":0.4892865816,"remaining_time":1.863052753},
{"learn":[0.13973458],"iteration":208,"passed_time":0.4932803124,"remaining_time":1.86691257},
{"learn":[0.1391878862],"iteration":209,"passed_time":0.4946070271,"remaining_time":1.860664531},
{"learn":[0.138743529],"iteration":210,"passed_time":0.4963049928,"remaining_time":1.855851371},
{"learn":[0.137917702],"iteration":211,"passed_time":0.4975152077,"remaining_time":1.84925464},
{"learn":[0.1372467004],"iteration":212,"passed_time":0.4988640444,"remaining_time":1.843220671},
{"learn":[0.1367972998],"iteration":213,"passed_time":0.500129371,"remaining_time":1.836923765},
{"learn":[0.1361728081],"iteration":214,"passed_time":0.5012363394,"remaining_time":1.830095472},
{"learn":[0.1356061239],"iteration":215,"passed_time":0.5027074216,"remaining_time":1.824641752},
{"learn":[0.1350652988],"iteration":216,"passed_time":0.5039521454,"remaining_time":1.818407972},
{"learn":[0.1344927824],"iteration":217,"passed_time":0.5053577207,"remaining_time":1.812796962},
{"learn":[0.1339388627],"iteration":218,"passed_time":0.5066101165,"remaining_time":1.806678087},
{"learn":[0.1333335271],"iteration":219,"passed_time":0.5079327289,"remaining_time":1.800852402},
{"learn":[0.1328073282],"iteration":220,"passed_time":0.5097305787,"remaining_time":1.796742628},
{"learn":[0.1323055854],"iteration":221,"passed_time":0.5114576546,"remaining_time":1.792405654},
{"learn":[0.1316643311],"iteration":222,"passed_time":0.5126371465,"remaining_time":1.786184138},
{"learn":[0.1309501208],"iteration":223,"passed_time":0.5149741338,"remaining_time":1.784017535},
{"learn":[0.1303366698],"iteration":224,"passed_time":0.5167149418,"remaining_time":1.779795911},
{"learn":[0.1297564965],"iteration":225,"passed_time":0.5190189726,"remaining_time":1.777525154},
{"learn":[0.1291373326],"iteration":226,"passed_time":0.5200334594,"remaining_time":1.770862838},
{"learn":[0.1284127052],"iteration":227,"passed_time":0.5210919597,"remaining_time":1.764399092},
{"learn":[0.1279658354],"iteration":228,"passed_time":0.5224206629,"remaining_time":1.758892276},
{"learn":[0.1274446524],"iteration":229,"passed_time":0.524176061,"remaining_time":1.754850291},
{"learn":[0.1270049902],"iteration":230,"passed_time":0.525957852,"remaining_time":1.750915966},
{"learn":[0.1265325271],"iteration":231,"passed_time":0.5291863308,"remaining_time":1.751789233},
{"learn":[0.1260956526],"iteration":232,"passed_time":0.531757757,"remaining_time":1.750464376},
{"learn":[0.1254490155],"iteration":233,"passed_time":0.5337807118,"remaining_time":1.747333441},
{"learn":[0.1249866027],"iteration":234,"passed_time":0.5357546884,"remaining_time":1.744052496},
{"learn":[0.1244885921],"iteration":235,"passed_time":0.5369602671,"remaining_time":1.738295102},
{"learn":[0.1239325083],"iteration":236,"passed_time":0.5381011239,"remaining_time":1.732367753},
{"learn":[0.1234540389],"iteration":237,"passed_time":0.53934551,"remaining_time":1.726812095},
{"learn":[0.1229115816],"iteration":238,"passed_time":0.5404439017,"remaining_time":1.720827654},
{"learn":[0.1224753215],"iteration":239,"passed_time":0.5424275941,"remaining_time":1.717687381},
{"learn":[0.1220877721],"iteration":240,"passed_time":0.5446459372,"remaining_time":1.715295711},
{"learn":[0.1216864494],"iteration":241,"passed_time":0.5460957522,"remaining_time":1.710498265},
{"learn":[0.1210848368],"iteration":242,"passed_time":0.5475137762,"remaining_time":1.705629336},
{"learn":[0.1206075412],"iteration":243,"passed_time":0.5497246721,"remaining_time":1.703245296},
{"learn":[0.1200595636],"iteration":244,"passed_time":0.552067435,"remaining_time":1.701269035},
{"learn":[0.1194759149],"iteration":245,"passed_time":0.5532894401,"remaining_time":1.695854625},
{"learn":[0.1189869551],"iteration":246,"passed_time":0.5544786244,"remaining_time":1.690374106},
{"learn":[0.1185146295],"iteration":247,"passed_time":0.5558040754,"remaining_time":1.68534139},
{"learn":[0.118055527],"iteration":248,"passed_time":0.5569366967,"remaining_time":1.679756864},
{"learn":[0.117452218],"iteration":249,"passed_time":0.5583961386,"remaining_time":1.675188416},
{"learn":[0.1169488797],"iteration":250,"passed_time":0.5596753268,"remaining_time":1.670106852},
{"learn":[0.1165984502],"iteration":251,"passed_time":0.5609947204,"remaining_time":1.665174805},
{"learn":[0.1161419245],"iteration":252,"passed_time":0.5632651815,"remaining_time":1.663079409},
{"learn":[0.1154869795],"iteration":253,"passed_time":0.5654600357,"remaining_time":1.660760577},
{"learn":[0.1149381032],"iteration":254,"passed_time":0.566816054,"remaining_time":1.655992001},
{"learn":[0.1146059403],"iteration":255,"passed_time":0.5678281949,"remaining_time":1.650250691},
{"learn":[0.1141457007],"iteration":256,"passed_time":0.5693271566,"remaining_time":1.645953608},
{"learn":[0.1137139155],"iteration":257,"passed_time":0.5702063724,"remaining_time":1.639895846},
{"learn":[0.1131562086],"iteration":258,"passed_time":0.5712869642,"remaining_time":1.63445421},
{"learn":[0.1126073874],"iteration":259,"passed_time":0.5746234156,"remaining_time":1.635466644},
{"learn":[0.112005839],"iteration":260,"passed_time":0.5769821909,"remaining_time":1.633677544},
{"learn":[0.111519676],"iteration":261,"passed_time":0.5785453528,"remaining_time":1.629643017},
{"learn":[0.1110807657],"iteration":262,"passed_time":0.5796299469,"remaining_time":1.624286201},
{"learn":[0.1107433117],"iteration":263,"passed_time":0.5808409639,"remaining_time":1.619314202},
{"learn":[0.1102986427],"iteration":264,"passed_time":0.5825426037,"remaining_time":1.615731372},
{"learn":[0.1099232344],"iteration":265,"passed_time":0.5837137054,"remaining_time":1.610698721},
{"learn":[0.1095410494],"iteration":266,"passed_time":0.5852100733,"remaining_time":1.606587954},
{"learn":[0.1091656685],"iteration":267,"passed_time":0.5864553254,"remaining_time":1.601810814},
{"learn":[0.1088130291],"iteration":268,"passed_time":0.5876484227,"remaining_time":1.596918204},
{"learn":[0.1083446283],"iteration":269,"passed_time":0.5893058958,"remaining_time":1.593308533},
{"learn":[0.1079609486],"iteration":270,"passed_time":0.5907922659,"remaining_time":1.589252996},
{"learn":[0.1075601486],"iteration":271,"passed_time":0.5920607279,"remaining_time":1.584633125},
{"learn":[0.1071789081],"iteration":272,"passed_time":0.5937410064,"remaining_time":1.581134475},
{"learn":[0.1067285079],"iteration":273,"passed_time":0.5959105421,"remaining_time":1.578945451},
{"learn":[0.1061178721],"iteration":274,"passed_time":0.5975193306,"remaining_time":1.575278235},
{"learn":[0.1057380438],"iteration":275,"passed_time":0.5987679116,"remaining_time":1.570681043},
{"learn":[0.1052377591],"iteration":276,"passed_time":0.6009736858,"remaining_time":1.568606407},
{"learn":[0.1048297607],"iteration":277,"passed_time":0.6024307851,"remaining_time":1.564586427},
{"learn":[0.1043916299],"iteration":278,"passed_time":0.6034909535,"remaining_time":1.559559059},
{"learn":[0.1038954075],"iteration":279,"passed_time":0.604760103,"remaining_time":1.555097408},
{"learn":[0.1034888854],"iteration":280,"passed_time":0.6057873012,"remaining_time":1.550039394},
{"learn":[0.1030652156],"iteration":281,"passed_time":0.6066942968,"remaining_time":1.544703919},
{"learn":[0.1028458797],"iteration":282,"passed_time":0.6103178585,"remaining_time":1.546282348},
{"learn":[0.1027062306],"iteration":283,"passed_time":0.6117900239,"remaining_time":1.542400201},
{"learn":[0.1023116295],"iteration":284,"passed_time":0.613463147,"remaining_time":1.539039123},
{"learn":[0.1019603748],"iteration":285,"passed_time":0.6155264842,"remaining_time":1.53666402},
{"learn":[0.1016314305],"iteration":286,"passed_time":0.617462771,"remaining_time":1.533975455},
{"learn":[0.1013177358],"iteration":287,"passed_time":0.618903224,"remaining_time":1.530066304},
{"learn":[0.1009865724],"iteration":288,"passed_time":0.620254352,"remaining_time":1.525954479},
{"learn":[0.1006267529],"iteration":289,"passed_time":0.6213787208,"remaining_time":1.521306523},
{"learn":[0.1003586696],"iteration":290,"passed_time":0.6243521284,"remaining_time":1.521187832},
{"learn":[0.09999428346],"iteration":291,"passed_time":0.62637338,"remaining_time":1.518740935},
{"learn":[0.0997222662],"iteration":292,"passed_time":0.6282326566,"remaining_time":1.515906103},
{"learn":[0.09937323057],"iteration":293,"passed_time":0.6299832017,"remaining_time":1.512816804},
{"learn":[0.0990423606],"iteration":294,"passed_time":0.6313595671,"remaining_time":1.508842355},
{"learn":[0.09865458195],"iteration":295,"passed_time":0.6328852937,"remaining_time":1.505240698},
{"learn":[0.09829693574],"iteration":296,"passed_time":0.6339648015,"remaining_time":1.50059682},
{"learn":[0.0978004749],"iteration":297,"passed_time":0.6353678262,"remaining_time":1.496738973},
{"learn":[0.09731127666],"iteration":298,"passed_time":0.6377439151,"remaining_time":1.495178878},
{"learn":[0.0968513122],"iteration":299,"passed_time":0.6390962344,"remaining_time":1.491224547},
{"learn":[0.09646630287],"iteration":300,"passed_time":0.6418257971,"remaining_time":1.490485821},
{"learn":[0.09602934581],"iteration":301,"passed_time":0.6438429694,"remaining_time":1.488087393},
{"learn":[0.09563266314],"iteration":302,"passed_time":0.6457072453,"remaining_time":1.485339769},
{"learn":[0.09519692568],"iteration":303,"passed_time":0.6471876913,"remaining_time":1.481719188},
{"learn":[0.09479906009],"iteration":304,"passed_time":0.6488918408,"remaining_time":1.478622391},
{"learn":[0.0945286384],"iteration":305,"passed_time":0.6507221285,"remaining_time":1.475820775},
{"learn":[0.09420921252],"iteration":306,"passed_time":0.6518147126,"remaining_time":1.471360247},
{"learn":[0.09389492182],"iteration":307,"passed_time":0.6528688982,"remaining_time":1.466835317},
{"learn":[0.09363621932],"iteration":308,"passed_time":0.6574770534,"remaining_time":1.470280401},
{"learn":[0.09337929579],"iteration":309,"passed_time":0.6590800487,"remaining_time":1.466984625},
{"learn":[0.09299138876],"iteration":310,"passed_time":0.660196852,"remaining_time":1.462622608},
{"learn":[0.09265693334],"iteration":311,"passed_time":0.6611999698,"remaining_time":1.458030703},
{"learn":[0.09225893021],"iteration":312,"passed_time":0.666006468,"remaining_time":1.461809724},
{"learn":[0.09201618341],"iteration":313,"passed_time":0.6676157557,"remaining_time":1.458549071},
{"learn":[0.09172393725],"iteration":314,"passed_time":0.6691225901,"remaining_time":1.455076109},
{"learn":[0.09144214483],"iteration":315,"passed_time":0.6709596182,"remaining_time":1.452330313},
{"learn":[0.09124157979],"iteration":316,"passed_time":0.6719352039,"remaining_time":1.447734209},
{"learn":[0.09081132595],"iteration":317,"passed_time":0.6729541246,"remaining_time":1.443253814},
{"learn":[0.09036517143],"iteration":318,"passed_time":0.6739335109,"remaining_time":1.438710724},
{"learn":[0.0900375843],"iteration":319,"passed_time":0.6763923526,"remaining_time":1.437333749},
{"learn":[0.08973825895],"iteration":320,"passed_time":0.6778054473,"remaining_time":1.433738002},
{"learn":[0.08950249965],"iteration":321,"passed_time":0.6801615848,"remaining_time":1.432141474},
{"learn":[0.08917377545],"iteration":322,"passed_time":0.6811544243,"remaining_time":1.427682803},
{"learn":[0.088786547],"iteration":323,"passed_time":0.6845341113,"remaining_time":1.428225491},
{"learn":[0.08850144423],"iteration":324,"passed_time":0.685828913,"remaining_time":1.424413896},
{"learn":[0.08823433289],"iteration":325,"passed_time":0.6868650502,"remaining_time":1.420082957},
{"learn":[0.08803471235],"iteration":326,"passed_time":0.6877180487,"remaining_time":1.41539525},
{"learn":[0.08776307106],"iteration":327,"passed_time":0.6889400165,"remaining_time":1.411486863},
{"learn":[0.0874806184],"iteration":328,"passed_time":0.6911529277,"remaining_time":1.40961585},
{"learn":[0.08714913405],"iteration":329,"passed_time":0.6927088939,"remaining_time":1.406408966},
{"learn":[0.08678710461],"iteration":330,"passed_time":0.6940250751,"remaining_time":1.402727418},
{"learn":[0.08647517975],"iteration":331,"passed_time":0.6959290795,"remaining_time":1.400242847},
{"learn":[0.08624968162],"iteration":332,"passed_time":0.7020481201,"remaining_time":1.406204493},
{"learn":[0.08592292896],"iteration":333,"passed_time":0.7035891406,"remaining_time":1.402965173},
{"learn":[0.08563140722],"iteration":334,"passed_time":0.7047334476,"remaining_time":1.398948486},
{"learn":[0.08520353757],"iteration":335,"passed_time":0.7065503826,"remaining_time":1.396278137},
{"learn":[0.08483241155],"iteration":336,"passed_time":0.7076089023,"remaining_time":1.392120778},
{"learn":[0.08457734035],"iteration":337,"passed_time":0.7098511327,"remaining_time":1.390300147},
{"learn":[0.08427777657],"iteration":338,"passed_time":0.7110526154,"remaining_time":1.386447725},
{"learn":[0.08404272336],"iteration":339,"passed_time":0.7152537595,"remaining_time":1.388433768},
{"learn":[0.08378292047],"iteration":340,"passed_time":0.7168043507,"remaining_time":1.385261194},
{"learn":[0.08343931345],"iteration":341,"passed_time":0.7183506383,"remaining_time":1.382089825},
{"learn":[0.08323370493],"iteration":342,"passed_time":0.7196515632,"remaining_time":1.37845795},
{"learn":[0.0829719305],"iteration":343,"passed_time":0.7206738053,"remaining_time":1.374308187},
{"learn":[0.08274554289],"iteration":344,"passed_time":0.7234461381,"remaining_time":1.37349919},
{"learn":[0.08247067378],"iteration":345,"passed_time":0.7246820725,"remaining_time":1.369774785},
{"learn":[0.08217113752],"iteration":346,"passed_time":0.7261455817,"remaining_time":1.366492982},
{"learn":[0.08186415526],"iteration":347,"passed_time":0.7284522215,"remaining_time":1.364801289},
{"learn":[0.08163033082],"iteration":348,"passed_time":0.7299025335,"remaining_time":1.361508737},
{"learn":[0.08136747434],"iteration":349,"passed_time":0.731342642,"remaining_time":1.358207764},
{"learn":[0.08098655481],"iteration":350,"passed_time":0.7328619965,"remaining_time":1.355063919},
{"learn":[0.08070434057],"iteration":351,"passed_time":0.7341520545,"remaining_time":1.351507191},
{"learn":[0.08040748193],"iteration":352,"passed_time":0.737159515,"remaining_time":1.351111066},
{"learn":[0.08017594081],"iteration":353,"passed_time":0.7388274137,"remaining_time":1.348255676},
{"learn":[0.07989350649],"iteration":354,"passed_time":0.7398521365,"remaining_time":1.344238389},
{"learn":[0.0796597279],"iteration":355,"passed_time":0.7410787855,"remaining_time":1.340603196},
{"learn":[0.07941084642],"iteration":356,"passed_time":0.7428061166,"remaining_time":1.337883286},
{"learn":[0.07909198908],"iteration":357,"passed_time":0.744244375,"remaining_time":1.334650527},
{"learn":[0.07878179734],"iteration":358,"passed_time":0.7452503834,"remaining_time":1.330655977},
{"learn":[0.07848310471],"iteration":359,"passed_time":0.7469960204,"remaining_time":1.327992925},
{"learn":[0.07822746497],"iteration":360,"passed_time":0.7480855155,"remaining_time":1.32417353},
{"learn":[0.0780037183],"iteration":361,"passed_time":0.7502552503,"remaining_time":1.322273065},
{"learn":[0.07775628567],"iteration":362,"passed_time":0.7514559209,"remaining_time":1.318670583},
{"learn":[0.07745588743],"iteration":363,"passed_time":0.7532399935,"remaining_time":1.316100648},
{"learn":[0.07724391497],"iteration":364,"passed_time":0.7544242351,"remaining_time":1.312491477},
{"learn":[0.07707845248],"iteration":365,"passed_time":0.7558892298,"remaining_time":1.30938189},
{"learn":[0.07675926502],"iteration":366,"passed_time":0.7574081197,"remaining_time":1.306374223},
{"learn":[0.07649250214],"iteration":367,"passed_time":0.7585038656,"remaining_time":1.302647943},
{"learn":[0.07625238712],"iteration":368,"passed_time":0.7595001805,"remaining_time":1.298765891},
{"learn":[0.0759964081],"iteration":369,"passed_time":0.7604654701,"remaining_time":1.294846611},
{"learn":[0.0757648303],"iteration":370,"passed_time":0.7614299643,"remaining_time":1.290941907},
{"learn":[0.07551561411],"iteration":371,"passed_time":0.7632924255,"remaining_time":1.288568933},
{"learn":[0.07532701584],"iteration":372,"passed_time":0.764335671,"remaining_time":1.284821624},
{"learn":[0.07507639206],"iteration":373,"passed_time":0.7653437635,"remaining_time":1.281029936},
{"learn":[0.07490431345],"iteration":374,"passed_time":0.7662908581,"remaining_time":1.27715143},
{"learn":[0.0746865731],"iteration":375,"passed_time":0.7672479654,"remaining_time":1.273305134},
{"learn":[0.07432449781],"iteration":376,"passed_time":0.7684187334,"remaining_time":1.269827244},
{"learn":[0.07414548672],"iteration":377,"passed_time":0.7695427718,"remaining_time":1.266284667},
{"learn":[0.07387385919],"iteration":378,"passed_time":0.770497657,"remaining_time":1.262477691},
{"learn":[0.07360661488],"iteration":379,"passed_time":0.771713639,"remaining_time":1.259111727},
{"learn":[0.07353397058],"iteration":380,"passed_time":0.772599402,"remaining_time":1.255220551},
{"learn":[0.07350497979],"iteration":381,"passed_time":0.773051097,"remaining_time":1.250642874},
{"learn":[0.07327661147],"iteration":382,"passed_time":0.7740940794,"remaining_time":1.247039287},
{"learn":[0.0730085648],"iteration":383,"passed_time":0.7763160657,"remaining_time":1.245340355},
{"learn":[0.07279980641],"iteration":384,"passed_time":0.777255955,"remaining_time":1.241590681},
{"learn":[0.07256165835],"iteration":385,"passed_time":0.7782815334,"remaining_time":1.237991869},
{"learn":[0.07227992094],"iteration":386,"passed_time":0.7792588714,"remaining_time":1.234329944},
{"learn":[0.07203436815],"iteration":387,"passed_time":0.7801056102,"remaining_time":1.230475859},
{"learn":[0.07174179646],"iteration":388,"passed_time":0.781202743,"remaining_time":1.227030529},
{"learn":[0.07158312431],"iteration":389,"passed_time":0.7827083817,"remaining_time":1.224236187},
{"learn":[0.07130801219],"iteration":390,"passed_time":0.7839613058,"remaining_time":1.221054822},
{"learn":[0.07112530562],"iteration":391,"passed_time":0.7850478932,"remaining_time":1.217625304},
{"learn":[0.07089139865],"iteration":392,"passed_time":0.7865636837,"remaining_time":1.214870626},
{"learn":[0.07067803236],"iteration":393,"passed_time":0.7879493464,"remaining_time":1.211922091},
{"learn":[0.07063010564],"iteration":394,"passed_time":0.7889646934,"remaining_time":1.208414277},
{"learn":[0.07030457717],"iteration":395,"passed_time":0.790094573,"remaining_time":1.205093743},
{"learn":[0.07001477021],"iteration":396,"passed_time":0.7911548709,"remaining_time":1.201678557},
{"learn":[0.06974294552],"iteration":397,"passed_time":0.7921070154,"remaining_time":1.198111616},
{"learn":[0.06956878992],"iteration":398,"passed_time":0.7931035149,"remaining_time":1.194624593},
{"learn":[0.06927052828],"iteration":399,"passed_time":0.7941258805,"remaining_time":1.191188821},
{"learn":[0.06912172758],"iteration":400,"passed_time":0.7951761397,"remaining_time":1.187806752},
{"learn":[0.06887130554],"iteration":401,"passed_time":0.7961264136,"remaining_time":1.184287551},
{"learn":[0.06867645337],"iteration":402,"passed_time":0.7971312405,"remaining_time":1.180861912},
{"learn":[0.06846465514],"iteration":403,"passed_time":0.7981296269,"remaining_time":1.177438757},
{"learn":[0.06829667091],"iteration":404,"passed_time":0.79906306,"remaining_time":1.17393215},
{"learn":[0.06807183761],"iteration":405,"passed_time":0.8007767561,"remaining_time":1.171579786},
{"learn":[0.0678891402],"iteration":406,"passed_time":0.8029808112,"remaining_time":1.169945015},
{"learn":[0.06773460828],"iteration":407,"passed_time":0.8040701114,"remaining_time":1.166689966},
{"learn":[0.06744840512],"iteration":408,"passed_time":0.8054913761,"remaining_time":1.163925191},
{"learn":[0.0672562214],"iteration":409,"passed_time":0.8066185116,"remaining_time":1.160743712},
{"learn":[0.06703143853],"iteration":410,"passed_time":0.8076319873,"remaining_time":1.157409344},
{"learn":[0.06686618695],"iteration":411,"passed_time":0.8089752325,"remaining_time":1.154556885},
{"learn":[0.06663359129],"iteration":412,"passed_time":0.8100294226,"remaining_time":1.151300898},
{"learn":[0.06649443278],"iteration":413,"passed_time":0.8110556282,"remaining_time":1.148015938},
{"learn":[0.06630410139],"iteration":414,"passed_time":0.81200933,"remaining_time":1.144639658},
{"learn":[0.06607128565],"iteration":415,"passed_time":0.8130337893,"remaining_time":1.141374358},
{"learn":[0.06591179738],"iteration":416,"passed_time":0.8140541847,"remaining_time":1.138114124},
{"learn":[0.0656309082],"iteration":417,"passed_time":0.81525725,"remaining_time":1.135118946},
{"learn":[0.065433195],"iteration":418,"passed_time":0.8167187722,"remaining_time":1.132490708},
{"learn":[0.06526705393],"iteration":419,"passed_time":0.8178228667,"remaining_time":1.129374435},
{"learn":[0.06507568634],"iteration":420,"passed_time":0.8189439412,"remaining_time":1.126291074},
{"learn":[0.06489992142],"iteration":421,"passed_time":0.8199126832,"remaining_time":1.123008367},
{"learn":[0.06464925179],"iteration":422,"passed_time":0.8211790901,"remaining_time":1.120142636},
{"learn":[0.06439628051],"iteration":423,"passed_time":0.8221654787,"remaining_time":1.116904047},
{"learn":[0.06426137227],"iteration":424,"passed_time":0.8232014961,"remaining_time":1.113743201},
{"learn":[0.06409369524],"iteration":425,"passed_time":0.8241939107,"remaining_time":1.110533579},
{"learn":[0.06390745823],"iteration":426,"passed_time":0.8251948529,"remaining_time":1.107345786},
{"learn":[0.06372196858],"iteration":427,"passed_time":0.8261690815,"remaining_time":1.104132511},
{"learn":[0.06350565874],"iteration":428,"passed_time":0.8274125197,"remaining_time":1.101287992},
{"learn":[0.06331899533],"iteration":429,"passed_time":0.8285684264,"remaining_time":1.098334891},
{"learn":[0.0631260826],"iteration":430,"passed_time":0.8295929505,"remaining_time":1.095216679},
{"learn":[0.06296581488],"iteration":431,"passed_time":0.8312717618,"remaining_time":1.092968428},
{"learn":[0.06281554699],"iteration":432,"passed_time":0.8322869771,"remaining_time":1.089853848},
{"learn":[0.06263193259],"iteration":433,"passed_time":0.8337873133,"remaining_time":1.087381611},
{"learn":[0.06246722662],"iteration":434,"passed_time":0.835011427,"remaining_time":1.084555072},
{"learn":[0.06232447808],"iteration":435,"passed_time":0.8360241892,"remaining_time":1.081462483},
{"learn":[0.06218422376],"iteration":436,"passed_time":0.8369125263,"remaining_time":1.078219113},
{"learn":[0.06192334799],"iteration":437,"passed_time":0.8379460526,"remaining_time":1.075172789},
{"learn":[0.06180399198],"iteration":438,"passed_time":0.8392958276,"remaining_time":1.072539771},
{"learn":[0.06167370539],"iteration":439,"passed_time":0.84032505,"remaining_time":1.069504609},
{"learn":[0.06152346042],"iteration":440,"passed_time":0.8418492449,"remaining_time":1.067105959},
{"learn":[0.06134752127],"iteration":441,"passed_time":0.8429446776,"remaining_time":1.064169978},
{"learn":[0.06111782789],"iteration":442,"passed_time":0.8440177736,"remaining_time":1.061214221},
{"learn":[0.06091955992],"iteration":443,"passed_time":0.8461552694,"remaining_time":1.059599842},
{"learn":[0.06073727975],"iteration":444,"passed_time":0.8472625072,"remaining_time":1.056698183},
{"learn":[0.06053315676],"iteration":445,"passed_time":0.8484593202,"remaining_time":1.053915837},
{"learn":[0.06032502651],"iteration":446,"passed_time":0.8494288293,"remaining_time":1.050859379},
{"learn":[0.06010318719],"iteration":447,"passed_time":0.8504276123,"remaining_time":1.047848308},
{"learn":[0.05997266219],"iteration":448,"passed_time":0.8514289295,"remaining_time":1.04484931},
{"learn":[0.05973661863],"iteration":449,"passed_time":0.8525390742,"remaining_time":1.041992202},
{"learn":[0.05950935987],"iteration":450,"passed_time":0.8544360853,"remaining_time":1.040100689},
{"learn":[0.05939906377],"iteration":451,"passed_time":0.8549921488,"remaining_time":1.036583402},
{"learn":[0.05924973121],"iteration":452,"passed_time":0.8560863619,"remaining_time":1.033729007},
{"learn":[0.05910746868],"iteration":453,"passed_time":0.8570656374,"remaining_time":1.030744137},
{"learn":[0.05897499965],"iteration":454,"passed_time":0.8581172203,"remaining_time":1.027854692},
{"learn":[0.05873712668],"iteration":455,"passed_time":0.8593567623,"remaining_time":1.025197541},
{"learn":[0.05852406759],"iteration":456,"passed_time":0.8609267199,"remaining_time":1.022939188},
{"learn":[0.05832808751],"iteration":457,"passed_time":0.8620653796,"remaining_time":1.020173441},
{"learn":[0.05816475245],"iteration":458,"passed_time":0.8631179908,"remaining_time":1.017313362},
{"learn":[0.0579945766],"iteration":459,"passed_time":0.8641819394,"remaining_time":1.014474451},
{"learn":[0.05785595912],"iteration":460,"passed_time":0.8658566815,"remaining_time":1.012357378},
{"learn":[0.05773382462],"iteration":461,"passed_time":0.8669916827,"remaining_time":1.009613691},
{"learn":[0.05758798122],"iteration":462,"passed_time":0.8683803562,"remaining_time":1.007171169},
{"learn":[0.05747116988],"iteration":463,"passed_time":0.8693812047,"remaining_time":1.004285185},
{"learn":[0.05735108486],"iteration":464,"passed_time":0.8703391869,"remaining_time":1.001357989},
{"learn":[0.05720270597],"iteration":465,"passed_time":0.8713638554,"remaining_time":0.9985156626},
{"learn":[0.05710163483],"iteration":466,"passed_time":0.8723028585,"remaining_time":0.9955833481},
{"learn":[0.05697640089],"iteration":467,"passed_time":0.8738687533,"remaining_time":0.9933721725},
{"learn":[0.05681075041],"iteration":468,"passed_time":0.8756829048,"remaining_time":0.991444824},
{"learn":[0.05667647032],"iteration":469,"passed_time":0.87664996,"remaining_time":0.9885627209},
{"learn":[0.05655339589],"iteration":470,"passed_time":0.877738469,"remaining_time":0.9858251594},
{"learn":[0.05635947448],"iteration":471,"passed_time":0.8787982617,"remaining_time":0.9830624622},
{"learn":[0.0562372391],"iteration":472,"passed_time":0.8797240006,"remaining_time":0.9801576075},
{"learn":[0.05604352401],"iteration":473,"passed_time":0.8810432083,"remaining_time":0.9776977374},
{"learn":[0.05583153321],"iteration":474,"passed_time":0.8820187404,"remaining_time":0.9748628184},
{"learn":[0.05568750088],"iteration":475,"passed_time":0.8829847875,"remaining_time":0.9720252702},
{"learn":[0.05556005239],"iteration":476,"passed_time":0.8839562095,"remaining_time":0.9692014624},
{"learn":[0.05545396988],"iteration":477,"passed_time":0.8848460392,"remaining_time":0.9662963022},
{"learn":[0.05533492565],"iteration":478,"passed_time":0.8857994701,"remaining_time":0.9634687347},
{"learn":[0.05524379932],"iteration":479,"passed_time":0.8863484502,"remaining_time":0.9602108211},
{"learn":[0.0550334316],"iteration":480,"passed_time":0.8873395077,"remaining_time":0.9574411736},
{"learn":[0.05493202118],"iteration":481,"passed_time":0.8883220317,"remaining_time":0.9546697353},
{"learn":[0.05478810806],"iteration":482,"passed_time":0.8893598527,"remaining_time":0.9519648941},
{"learn":[0.05459299454],"iteration":483,"passed_time":0.8908132983,"remaining_time":0.9497100453},
{"learn":[0.05446409721],"iteration":484,"passed_time":0.8917867999,"remaining_time":0.94694887},
{"learn":[0.05433340256],"iteration":485,"passed_time":0.8933229346,"remaining_time":0.9447900996},
{"learn":[0.05423335387],"iteration":486,"passed_time":0.894624204,"remaining_time":0.9423864818},
{"learn":[0.05412218662],"iteration":487,"passed_time":0.8957478417,"remaining_time":0.9398010142},
{"learn":[0.053930035],"iteration":488,"passed_time":0.8969515554,"remaining_time":0.9373052042},
{"learn":[0.05372663645],"iteration":489,"passed_time":0.8979527141,"remaining_time":0.9346038453},
{"learn":[0.05360397467],"iteration":490,"passed_time":0.8990356148,"remaining_time":0.9319941506},
{"learn":[0.05348345408],"iteration":491,"passed_time":0.900212702,"remaining_time":0.9294879118},
{"learn":[0.05332532296],"iteration":492,"passed_time":0.9014851499,"remaining_time":0.9270851339},
{"learn":[0.05322066637],"iteration":493,"passed_time":0.9026519871,"remaining_time":0.924578756},
{"learn":[0.05304875741],"iteration":494,"passed_time":0.9036275051,"remaining_time":0.9218826062},
{"learn":[0.052945082],"iteration":495,"passed_time":0.9049202276,"remaining_time":0.9195157151},
{"learn":[0.05276896403],"iteration":496,"passed_time":0.9060225531,"remaining_time":0.9169604511},
{"learn":[0.05263167161],"iteration":497,"passed_time":0.9070937588,"remaining_time":0.9143796525},
{"learn":[0.05258186964],"iteration":498,"passed_time":0.9075554062,"remaining_time":0.9111929028},
{"learn":[0.0523912494],"iteration":499,"passed_time":0.9085052992,"remaining_time":0.9085052992},
{"learn":[0.05225414496],"iteration":500,"passed_time":0.9094748567,"remaining_time":0.9058442185},
{"learn":[0.05212975465],"iteration":501,"passed_time":0.9105033242,"remaining_time":0.9032483176},
{"learn":[0.0520018706],"iteration":502,"passed_time":0.9115759216,"remaining_time":0.9007022526},
{"learn":[0.05186339525],"iteration":503,"passed_time":0.9125847656,"remaining_time":0.8980992932},
{"learn":[0.0517705954],"iteration":504,"passed_time":0.9139846467,"remaining_time":0.8958859409},
{"learn":[0.05164033175],"iteration":505,"passed_time":0.9150983652,"remaining_time":0.8933964277},
{"learn":[0.05154346961],"iteration":506,"passed_time":0.9160875439,"remaining_time":0.890791241},
{"learn":[0.05140853387],"iteration":507,"passed_time":0.9171003068,"remaining_time":0.8882152578},
{"learn":[0.05126430897],"iteration":508,"passed_time":0.9182273192,"remaining_time":0.8857556262},
{"learn":[0.05114986805],"iteration":509,"passed_time":0.9194924802,"remaining_time":0.8834339516},
{"learn":[0.05098087054],"iteration":510,"passed_time":0.9209490318,"remaining_time":0.8812995627},
{"learn":[0.05084503614],"iteration":511,"passed_time":0.9220645226,"remaining_time":0.8788427481},
{"learn":[0.05073264929],"iteration":512,"passed_time":0.9235869284,"remaining_time":0.8767774545},
{"learn":[0.0506272912],"iteration":513,"passed_time":0.9245467351,"remaining_time":0.8741823216},
{"learn":[0.05044438747],"iteration":514,"passed_time":0.9255999215,"remaining_time":0.8716814794},
{"learn":[0.0503174846],"iteration":515,"passed_time":0.9265385682,"remaining_time":0.869078812},
{"learn":[0.05017762918],"iteration":516,"passed_time":0.9277888962,"remaining_time":0.8667737657},
{"learn":[0.04996531743],"iteration":517,"passed_time":0.9288185259,"remaining_time":0.8642674315},
{"learn":[0.04987058273],"iteration":518,"passed_time":0.9299027365,"remaining_time":0.8618173724},
{"learn":[0.04976407381],"iteration":519,"passed_time":0.9310774439,"remaining_time":0.859456102},
{"learn":[0.04964684982],"iteration":520,"passed_time":0.9324664686,"remaining_time":0.857296427},
{"learn":[0.04952935072],"iteration":521,"passed_time":0.9340945413,"remaining_time":0.855358603},
{"learn":[0.04939899536],"iteration":522,"passed_time":0.9353204061,"remaining_time":0.8530551314},
{"learn":[0.04929611316],"iteration":523,"passed_time":0.9375506004,"remaining_time":0.8516681027},
{"learn":[0.04920628438],"iteration":524,"passed_time":0.9386133009,"remaining_time":0.849221558},
{"learn":[0.04903103297],"iteration":525,"passed_time":0.9396097825,"remaining_time":0.8467206025},
{"learn":[0.04881521372],"iteration":526,"passed_time":0.9407808522,"remaining_time":0.8443820552},
{"learn":[0.04873435772],"iteration":527,"passed_time":0.9418141472,"remaining_time":0.8419247679},
{"learn":[0.04864015488],"iteration":528,"passed_time":0.942758465,"remaining_time":0.8393936427},
{"learn":[0.04853625022],"iteration":529,"passed_time":0.9437994642,"remaining_time":0.8369542418},
{"learn":[0.04843787964],"iteration":530,"passed_time":0.9452205622,"remaining_time":0.8348558261},
{"learn":[0.04833269119],"iteration":531,"passed_time":0.9462771403,"remaining_time":0.8324392888},
{"learn":[0.04821985502],"iteration":532,"passed_time":0.9474872324,"remaining_time":0.8301623593},
{"learn":[0.04812850402],"iteration":533,"passed_time":0.9489462051,"remaining_time":0.8281066135},
{"learn":[0.04802305882],"iteration":534,"passed_time":0.9500969485,"remaining_time":0.8257851983},
{"learn":[0.04790394581],"iteration":535,"passed_time":0.9513023219,"remaining_time":0.8235154428},
{"learn":[0.04777996357],"iteration":536,"passed_time":0.9522347454,"remaining_time":0.8210143149},
{"learn":[0.04766201056],"iteration":537,"passed_time":0.9534316276,"remaining_time":0.8187461189},
{"learn":[0.04757367648],"iteration":538,"passed_time":0.9547008508,"remaining_time":0.8165437703},
{"learn":[0.04749223361],"iteration":539,"passed_time":0.9556550823,"remaining_time":0.8140765516},
{"learn":[0.04739541274],"iteration":540,"passed_time":0.9570108473,"remaining_time":0.8119555987},
{"learn":[0.04725962877],"iteration":541,"passed_time":0.9581921968,"remaining_time":0.8096900851},
{"learn":[0.0471361417],"iteration":542,"passed_time":0.959183566,"remaining_time":0.8072686734},
{"learn":[0.04702619406],"iteration":543,"passed_time":0.9616289646,"remaining_time":0.8060713379},
{"learn":[0.04691479756],"iteration":544,"passed_time":0.9626262155,"remaining_time":0.8036604185},
{"learn":[0.04681808215],"iteration":545,"passed_time":0.9641710526,"remaining_time":0.8017099961},
{"learn":[0.04670449404],"iteration":546,"passed_time":0.9651435394,"remaining_time":0.7992870628},
{"learn":[0.04656946659],"iteration":547,"passed_time":0.9660806184,"remaining_time":0.7968402181},
{"learn":[0.04648603843],"iteration":548,"passed_time":0.9674506152,"remaining_time":0.7947545126},
{"learn":[0.04639005661],"iteration":549,"passed_time":0.9684088772,"remaining_time":0.7923345359},
{"learn":[0.04630838908],"iteration":550,"passed_time":0.9694510025,"remaining_time":0.7899882035},
{"learn":[0.04621094924],"iteration":551,"passed_time":0.9704348033,"remaining_time":0.7875992607},
{"learn":[0.04610911241],"iteration":552,"passed_time":0.9715895746,"remaining_time":0.7853535983},
{"learn":[0.04599694105],"iteration":553,"passed_time":0.9725291611,"remaining_time":0.7829386387},
{"learn":[0.04588788748],"iteration":554,"passed_time":0.9735347045,"remaining_time":0.7805818801},
{"learn":[0.04581387226],"iteration":555,"passed_time":0.9744755416,"remaining_time":0.7781783102},
{"learn":[0.04573832108],"iteration":556,"passed_time":0.9753937456,"remaining_time":0.7757619915},
{"learn":[0.04558925445],"iteration":557,"passed_time":0.9762864703,"remaining_time":0.77333086},
{"learn":[0.04547832562],"iteration":558,"passed_time":0.9777545978,"remaining_time":0.7713591729},
{"learn":[0.04539143581],"iteration":559,"passed_time":0.979218895,"remaining_time":0.7693862746},
{"learn":[0.04530106141],"iteration":560,"passed_time":0.9806181117,"remaining_time":0.7673642621},
{"learn":[0.04515679983],"iteration":561,"passed_time":0.9815717041,"remaining_time":0.7649971644},
{"learn":[0.04506812646],"iteration":562,"passed_time":0.9825513628,"remaining_time":0.7626553206},
{"learn":[0.04495660617],"iteration":563,"passed_time":0.9848209619,"remaining_time":0.7613154954},
{"learn":[0.04485969819],"iteration":564,"passed_time":0.9857922135,"remaining_time":0.7589727662},
{"learn":[0.04476894782],"iteration":565,"passed_time":0.9874543373,"remaining_time":0.7571646332},
{"learn":[0.04462286142],"iteration":566,"passed_time":0.9884988674,"remaining_time":0.7548853784},
{"learn":[0.0445365218],"iteration":567,"passed_time":0.9896213767,"remaining_time":0.7526697795},
{"learn":[0.04444246109],"iteration":568,"passed_time":0.9906038278,"remaining_time":0.7503519328},
{"learn":[0.04431987726],"iteration":569,"passed_time":0.9917326724,"remaining_time":0.748149209},
{"learn":[0.04421541324],"iteration":570,"passed_time":0.9928588067,"remaining_time":0.7459482103},
{"learn":[0.04413033907],"iteration":571,"passed_time":0.9945832807,"remaining_time":0.7441986785},
{"learn":[0.04403833243],"iteration":572,"passed_time":0.9955717333,"remaining_time":0.7419007506},
{"learn":[0.04394743534],"iteration":573,"passed_time":0.9967229294,"remaining_time":0.7397281671},
{"learn":[0.043806397],"iteration":574,"passed_time":0.9980867212,"remaining_time":0.7377162722},
{"learn":[0.04368464763],"iteration":575,"passed_time":0.9992199813,"remaining_time":0.7355369307},
{"learn":[0.04353703902],"iteration":576,"passed_time":1.000780717,"remaining_time":0.7336745986},
{"learn":[0.04344722858],"iteration":577,"passed_time":1.001776333,"remaining_time":0.7314007136},
{"learn":[0.04335444707],"iteration":578,"passed_time":1.002797741,"remaining_time":0.7291499981},
{"learn":[0.04325943727],"iteration":579,"passed_time":1.003769484,"remaining_time":0.7268675576},
{"learn":[0.04313296538],"iteration":580,"passed_time":1.004670216,"remaining_time":0.7245384177},
{"learn":[0.04306267775],"iteration":581,"passed_time":1.00565512,"remaining_time":0.7222746394},
{"learn":[0.04297781908],"iteration":582,"passed_time":1.006724111,"remaining_time":0.720075393},
{"learn":[0.04288672025],"iteration":583,"passed_time":1.007695734,"remaining_time":0.7178106595},
{"learn":[0.04275844647],"iteration":584,"passed_time":1.009685359,"remaining_time":0.7162725199},
{"learn":[0.04264472998],"iteration":585,"passed_time":1.011724102,"remaining_time":0.71476754},
{"learn":[0.04254795955],"iteration":586,"passed_time":1.012758153,"remaining_time":0.712553862},
{"learn":[0.04247338955],"iteration":587,"passed_time":1.014185969,"remaining_time":0.7106201007},
{"learn":[0.04237427161],"iteration":588,"passed_time":1.015213798,"remaining_time":0.7084089491},
{"learn":[0.04229230606],"iteration":589,"passed_time":1.017267996,"remaining_time":0.7069150482},
{"learn":[0.04220473766],"iteration":590,"passed_time":1.018209613,"remaining_time":0.7046492924},
{"learn":[0.04212050255],"iteration":591,"passed_time":1.019186787,"remaining_time":0.7024125157},
{"learn":[0.04205369032],"iteration":592,"passed_time":1.020505561,"remaining_time":0.7004144406},
{"learn":[0.04198056918],"iteration":593,"passed_time":1.021434955,"remaining_time":0.6981525111},
{"learn":[0.04190141421],"iteration":594,"passed_time":1.022361487,"remaining_time":0.6958931128},
{"learn":[0.04175510773],"iteration":595,"passed_time":1.023889264,"remaining_time":0.6940457426},
{"learn":[0.04164813115],"iteration":596,"passed_time":1.024802582,"remaining_time":0.6917846573},
{"learn":[0.04156065446],"iteration":597,"passed_time":1.025694712,"remaining_time":0.6895138365},
{"learn":[0.04149295734],"iteration":598,"passed_time":1.027035822,"remaining_time":0.6875481881},
{"learn":[0.04140360539],"iteration":599,"passed_time":1.027957978,"remaining_time":0.6853053185},
{"learn":[0.04131925106],"iteration":600,"passed_time":1.029036004,"remaining_time":0.6831703258},
{"learn":[0.04123381468],"iteration":601,"passed_time":1.030056334,"remaining_time":0.6810006995},
{"learn":[0.04112513707],"iteration":602,"passed_time":1.031178717,"remaining_time":0.6789020742},
{"learn":[0.04103641327],"iteration":603,"passed_time":1.032080862,"remaining_time":0.6766622868},
{"learn":[0.04096573591],"iteration":604,"passed_time":1.033066615,"remaining_time":0.6744815088},
{"learn":[0.04086362857],"iteration":605,"passed_time":1.034290867,"remaining_time":0.6724597386},
{"learn":[0.04077527156],"iteration":606,"passed_time":1.035268132,"remaining_time":0.6702806851},
{"learn":[0.0406911419],"iteration":607,"passed_time":1.03618967,"remaining_time":0.6680696557},
{"learn":[0.04058820468],"iteration":608,"passed_time":1.037310706,"remaining_time":0.665990946},
{"learn":[0.04053011307],"iteration":609,"passed_time":1.038500568,"remaining_time":0.6639593793},
{"learn":[0.04045625375],"iteration":610,"passed_time":1.039630697,"remaining_time":0.6618925385},
{"learn":[0.04035769976],"iteration":611,"passed_time":1.041244974,"remaining_time":0.6601357023},
{"learn":[0.04028019538],"iteration":612,"passed_time":1.042419207,"remaining_time":0.6581015223},
{"learn":[0.04020468088],"iteration":613,"passed_time":1.043462995,"remaining_time":0.6559881367},
{"learn":[0.04011200025],"iteration":614,"passed_time":1.04459904,"remaining_time":0.6539359847},
{"learn":[0.04000712817],"iteration":615,"passed_time":1.045690373,"remaining_time":0.6518589341},
{"learn":[0.03992452071],"iteration":616,"passed_time":1.046849369,"remaining_time":0.6498270802},
{"learn":[0.03981678302],"iteration":617,"passed_time":1.04799563,"remaining_time":0.6477901793},
{"learn":[0.0397240382],"iteration":618,"passed_time":1.049203911,"remaining_time":0.64579433},
{"learn":[0.03966016953],"iteration":619,"passed_time":1.050726664,"remaining_time":0.6439937618},
{"learn":[0.03959639256],"iteration":620,"passed_time":1.051581247,"remaining_time":0.6417863003},
{"learn":[0.0394462347],"iteration":621,"passed_time":1.053916039,"remaining_time":0.6404827377},
{"learn":[0.03938089884],"iteration":622,"passed_time":1.055432991,"remaining_time":0.638680959},
{"learn":[0.03926683389],"iteration":623,"passed_time":1.056392618,"remaining_time":0.6365442698},
{"learn":[0.03917586803],"iteration":624,"passed_time":1.057696505,"remaining_time":0.6346179031},
{"learn":[0.03906462284],"iteration":625,"passed_time":1.058749576,"remaining_time":0.6325436765},
{"learn":[0.03894972801],"iteration":626,"passed_time":1.059881065,"remaining_time":0.6305193575},
{"learn":[0.0388883444],"iteration":627,"passed_time":1.061045486,"remaining_time":0.6285173896},
{"learn":[0.03882991351],"iteration":628,"passed_time":1.061975946,"remaining_time":0.6263800887},
{"learn":[0.03875752596],"iteration":629,"passed_time":1.063209756,"remaining_time":0.6244247776},
{"learn":[0.03868042047],"iteration":630,"passed_time":1.06425365,"remaining_time":0.6223606925},
{"learn":[0.03855823554],"iteration":631,"passed_time":1.065297696,"remaining_time":0.6202999243},
{"learn":[0.03847697148],"iteration":632,"passed_time":1.066299624,"remaining_time":0.6182179495},
{"learn":[0.03833340452],"iteration":633,"passed_time":1.067536508,"remaining_time":0.6162750188},
{"learn":[0.03824789707],"iteration":634,"passed_time":1.068623437,"remaining_time":0.6142481173},
{"learn":[0.0381957476],"iteration":635,"passed_time":1.069570767,"remaining_time":0.6121442752},
{"learn":[0.03811154916],"iteration":636,"passed_time":1.070668487,"remaining_time":0.6101297659},
{"learn":[0.03804674745],"iteration":637,"passed_time":1.071690208,"remaining_time":0.6080750086},
{"learn":[0.03797324804],"iteration":638,"passed_time":1.072541573,"remaining_time":0.6059272424},
{"learn":[0.0379038178],"iteration":639,"passed_time":1.074082515,"remaining_time":0.6041714149},
{"learn":[0.03780391125],"iteration":640,"passed_time":1.075169136,"remaining_time":0.6021618092},
{"learn":[0.03771245938],"iteration":641,"passed_time":1.07609462,"remaining_time":0.6000652243},
{"learn":[0.03765404224],"iteration":642,"passed_time":1.077132523,"remaining_time":0.598034698},
{"learn":[0.03758323651],"iteration":643,"passed_time":1.078094736,"remaining_time":0.5959654132},
{"learn":[0.03749042749],"iteration":644,"passed_time":1.079112356,"remaining_time":0.5939300565},
{"learn":[0.03742168958],"iteration":645,"passed_time":1.080331506,"remaining_time":0.5920082864},
{"learn":[0.03731884406],"iteration":646,"passed_time":1.081499805,"remaining_time":0.5900609448},
{"learn":[0.0372088391],"iteration":647,"passed_time":1.082978728,"remaining_time":0.588284741},
{"learn":[0.03712830406],"iteration":648,"passed_time":1.084118259,"remaining_time":0.5863258996},
{"learn":[0.03704056602],"iteration":649,"passed_time":1.085080289,"remaining_time":0.5842740016},
{"learn":[0.0369733572],"iteration":650,"passed_time":1.086093549,"remaining_time":0.5822529162},
{"learn":[0.03688599284],"iteration":651,"passed_time":1.087111061,"remaining_time":0.580237192},
{"learn":[0.03682484077],"iteration":652,"passed_time":1.090977192,"remaining_time":0.5797382626},
{"learn":[0.03676477304],"iteration":653,"passed_time":1.09199769,"remaining_time":0.5777235484},
{"learn":[0.03665889456],"iteration":654,"passed_time":1.093318356,"remaining_time":0.5758699736},
{"learn":[0.03658517507],"iteration":655,"passed_time":1.09441534,"remaining_time":0.5739007269},
{"learn":[0.03650829196],"iteration":656,"passed_time":1.096346155,"remaining_time":0.5723694539},
{"learn":[0.03639821364],"iteration":657,"passed_time":1.098072801,"remaining_time":0.5707308479},
{"learn":[0.03633265312],"iteration":658,"passed_time":1.099147305,"remaining_time":0.5687545237},
{"learn":[0.03622439274],"iteration":659,"passed_time":1.100576238,"remaining_time":0.5669635165},
{"learn":[0.03612296398],"iteration":660,"passed_time":1.101523577,"remaining_time":0.5649266153},
{"learn":[0.03604226617],"iteration":661,"passed_time":1.102443946,"remaining_time":0.5628792351},
{"learn":[0.03597389735],"iteration":662,"passed_time":1.103408743,"remaining_time":0.5608578376},
{"learn":[0.0358691376],"iteration":663,"passed_time":1.104351949,"remaining_time":0.5588286971},
{"learn":[0.03579979218],"iteration":664,"passed_time":1.105303424,"remaining_time":0.5568069879},
{"learn":[0.03571593991],"iteration":665,"passed_time":1.106222623,"remaining_time":0.5547723062},
{"learn":[0.03565981755],"iteration":666,"passed_time":1.107307903,"remaining_time":0.5528238858},
{"learn":[0.03555496381],"iteration":667,"passed_time":1.108209913,"remaining_time":0.5507869628},
{"learn":[0.03545620579],"iteration":668,"passed_time":1.109175166,"remaining_time":0.5487847235},
{"learn":[0.03544391577],"iteration":669,"passed_time":1.109624798,"remaining_time":0.5465316169},
{"learn":[0.03537590458],"iteration":670,"passed_time":1.110813275,"remaining_time":0.5446461511},
{"learn":[0.03527686229],"iteration":671,"passed_time":1.112055562,"remaining_time":0.5427890244},
{"learn":[0.03518805366],"iteration":672,"passed_time":1.113621994,"remaining_time":0.5410912216},
{"learn":[0.03511607418],"iteration":673,"passed_time":1.114928077,"remaining_time":0.5392678828},
{"learn":[0.03504178157],"iteration":674,"passed_time":1.116255739,"remaining_time":0.5374564671},
{"learn":[0.03497360303],"iteration":675,"passed_time":1.117352095,"remaining_time":0.5355356197},
{"learn":[0.03490766654],"iteration":676,"passed_time":1.118406758,"remaining_time":0.5335973158},
{"learn":[0.03481844985],"iteration":677,"passed_time":1.119618414,"remaining_time":0.5317361788},
{"learn":[0.03468259252],"iteration":678,"passed_time":1.120894217,"remaining_time":0.5299072809},
{"learn":[0.03460234862],"iteration":679,"passed_time":1.121888579,"remaining_time":0.5279475666},
{"learn":[0.03452805831],"iteration":680,"passed_time":1.122798531,"remaining_time":0.5259511473},
{"learn":[0.03446463897],"iteration":681,"passed_time":1.12374643,"remaining_time":0.523975608},
{"learn":[0.03435450105],"iteration":682,"passed_time":1.124684841,"remaining_time":0.5219986742},
{"learn":[0.03429566897],"iteration":683,"passed_time":1.125680347,"remaining_time":0.5200511547},
{"learn":[0.03425300121],"iteration":684,"passed_time":1.126999339,"remaining_time":0.5182551703},
{"learn":[0.03419887561],"iteration":685,"passed_time":1.128711394,"remaining_time":0.5166404921},
{"learn":[0.03415741141],"iteration":686,"passed_time":1.130288411,"remaining_time":0.5149640067},
{"learn":[0.03408299501],"iteration":687,"passed_time":1.13132387,"remaining_time":0.5130422202},
{"learn":[0.03401610943],"iteration":688,"passed_time":1.132484669,"remaining_time":0.5111795821},
{"learn":[0.033909573],"iteration":689,"passed_time":1.13436938,"remaining_time":0.5096442143},
{"learn":[0.03382668816],"iteration":690,"passed_time":1.135429882,"remaining_time":0.5077392672},
{"learn":[0.0337761205],"iteration":691,"passed_time":1.136505086,"remaining_time":0.5058433041},
{"learn":[0.03371321926],"iteration":692,"passed_time":1.137654081,"remaining_time":0.5039823996},
{"learn":[0.03362595577],"iteration":693,"passed_time":1.138813657,"remaining_time":0.5021282118},
{"learn":[0.03353164288],"iteration":694,"passed_time":1.140415804,"remaining_time":0.500470245},
{"learn":[0.03347124503],"iteration":695,"passed_time":1.141556388,"remaining_time":0.4986108362},
{"learn":[0.03342395562],"iteration":696,"passed_time":1.142506298,"remaining_time":0.4966706002},
{"learn":[0.03334619678],"iteration":697,"passed_time":1.143610044,"remaining_time":0.494799761},
{"learn":[0.0332314395],"iteration":698,"passed_time":1.144753058,"remaining_time":0.4929480262},
{"learn":[0.0331560786],"iteration":699,"passed_time":1.145754547,"remaining_time":0.4910376632},
{"learn":[0.03309096969],"iteration":700,"passed_time":1.147328572,"remaining_time":0.4893740986},
{"learn":[0.03301828183],"iteration":701,"passed_time":1.149269344,"remaining_time":0.4878664736},
{"learn":[0.03296193022],"iteration":702,"passed_time":1.150314426,"remaining_time":0.4859792099},
{"learn":[0.03287441226],"iteration":703,"passed_time":1.151401223,"remaining_time":0.4841118777},
{"learn":[0.03280972747],"iteration":704,"passed_time":1.152359297,"remaining_time":0.4821928974},
{"learn":[0.03273329139],"iteration":705,"passed_time":1.153975675,"remaining_time":0.4805507768},
{"learn":[0.03266408352],"iteration":706,"passed_time":1.155194027,"remaining_time":0.4787437766},
{"learn":[0.03260529729],"iteration":707,"passed_time":1.156222984,"remaining_time":0.4768603267},
{"learn":[0.03255674243],"iteration":708,"passed_time":1.157328217,"remaining_time":0.4750105941},
{"learn":[0.03250501706],"iteration":709,"passed_time":1.158243148,"remaining_time":0.4730852295},
{"learn":[0.03244714554],"iteration":710,"passed_time":1.159222036,"remaining_time":0.4711887037},
{"learn":[0.0323887284],"iteration":711,"passed_time":1.160445469,"remaining_time":0.4693936728},
{"learn":[0.03232304866],"iteration":712,"passed_time":1.161594179,"remaining_time":0.4675701673},
{"learn":[0.03226350592],"iteration":713,"passed_time":1.162758939,"remaining_time":0.4657549811},
{"learn":[0.03219142327],"iteration":714,"passed_time":1.163694661,"remaining_time":0.4638503196},
{"learn":[0.03210455179],"iteration":715,"passed_time":1.164604261,"remaining_time":0.4619380031},
{"learn":[0.0320660747],"iteration":716,"passed_time":1.165593363,"remaining_time":0.4600598631},
{"learn":[0.0319941319],"iteration":717,"passed_time":1.167711534,"remaining_time":0.4586276497},
{"learn":[0.03190685236],"iteration":718,"passed_time":1.168942063,"remaining_time":0.4568466199},
{"learn":[0.03182664743],"iteration":719,"passed_time":1.169922711,"remaining_time":0.4549699432},
{"learn":[0.03175528691],"iteration":720,"passed_time":1.171515108,"remaining_time":0.453332476},
{"learn":[0.03169312615],"iteration":721,"passed_time":1.172758839,"remaining_time":0.4515608825},
{"learn":[0.03162108935],"iteration":722,"passed_time":1.174654972,"remaining_time":0.4500407015},
{"learn":[0.03155386219],"iteration":723,"passed_time":1.175893573,"remaining_time":0.4482688205},
{"learn":[0.03148312523],"iteration":724,"passed_time":1.177036085,"remaining_time":0.4464619634},
{"learn":[0.03140802108],"iteration":725,"passed_time":1.17806852,"remaining_time":0.4446153919},
{"learn":[0.03135874409],"iteration":726,"passed_time":1.180489463,"remaining_time":0.4432924668},
{"learn":[0.03128308975],"iteration":727,"passed_time":1.181756386,"remaining_time":0.4415353531},
{"learn":[0.03122377166],"iteration":728,"passed_time":1.182755134,"remaining_time":0.4396798921},
{"learn":[0.03117005183],"iteration":729,"passed_time":1.183905067,"remaining_time":0.437882696},
{"learn":[0.03111881935],"iteration":730,"passed_time":1.184908298,"remaining_time":0.4360332861},
{"learn":[0.03104287386],"iteration":731,"passed_time":1.188525339,"remaining_time":0.4351431569},
{"learn":[0.03099063727],"iteration":732,"passed_time":1.189606055,"remaining_time":0.4333217145},
{"learn":[0.03093247459],"iteration":733,"passed_time":1.19068232,"remaining_time":0.4315006774},
{"learn":[0.03088518289],"iteration":734,"passed_time":1.191678956,"remaining_time":0.4296529569},
{"learn":[0.03082919579],"iteration":735,"passed_time":1.192632184,"remaining_time":0.427791979},
{"learn":[0.03074304186],"iteration":736,"passed_time":1.193661759,"remaining_time":0.4259607089},
{"learn":[0.03069149072],"iteration":737,"passed_time":1.194638053,"remaining_time":0.4241126964},
{"learn":[0.03064293816],"iteration":738,"passed_time":1.195810436,"remaining_time":0.4223362973},
{"learn":[0.03058239359],"iteration":739,"passed_time":1.19681977,"remaining_time":0.4205042435},
{"learn":[0.03047902309],"iteration":740,"passed_time":1.197905839,"remaining_time":0.4187012313},
{"learn":[0.03036250289],"iteration":741,"passed_time":1.199818783,"remaining_time":0.4171876632},
{"learn":[0.03029369391],"iteration":742,"passed_time":1.202209997,"remaining_time":0.4158384512},
{"learn":[0.03024987533],"iteration":743,"passed_time":1.203261748,"remaining_time":0.4140255478},
{"learn":[0.03020207928],"iteration":744,"passed_time":1.204199577,"remaining_time":0.4121756942},
{"learn":[0.03014979454],"iteration":745,"passed_time":1.205419263,"remaining_time":0.4104242531},
{"learn":[0.03009661344],"iteration":746,"passed_time":1.20682469,"remaining_time":0.4087371441},
{"learn":[0.03005157067],"iteration":747,"passed_time":1.207873441,"remaining_time":0.4069306246},
{"learn":[0.03000463431],"iteration":748,"passed_time":1.208838503,"remaining_time":0.4050980832},
{"learn":[0.02994390634],"iteration":749,"passed_time":1.209817156,"remaining_time":0.4032723853},
{"learn":[0.02989982412],"iteration":750,"passed_time":1.210879869,"remaining_time":0.4014768141},
{"learn":[0.02982592124],"iteration":751,"passed_time":1.21189209,"remaining_time":0.3996665402},
{"learn":[0.02978423696],"iteration":752,"passed_time":1.212983746,"remaining_time":0.3978844427},
{"learn":[0.02973085642],"iteration":753,"passed_time":1.214006369,"remaining_time":0.3960816536},
{"learn":[0.02967651074],"iteration":754,"passed_time":1.214929176,"remaining_time":0.3942485405},
{"learn":[0.02961990925],"iteration":755,"passed_time":1.216176876,"remaining_time":0.3925226953},
{"learn":[0.02955794793],"iteration":756,"passed_time":1.217205942,"remaining_time":0.3907279312},
{"learn":[0.02948669745],"iteration":757,"passed_time":1.218318837,"remaining_time":0.3889619505},
{"learn":[0.02942701945],"iteration":758,"passed_time":1.219866056,"remaining_time":0.3873355987},
{"learn":[0.02937941826],"iteration":759,"passed_time":1.221033817,"remaining_time":0.3855896264},
{"learn":[0.0293373924],"iteration":760,"passed_time":1.222040194,"remaining_time":0.3837944892},
{"learn":[0.02927987621],"iteration":761,"passed_time":1.222936381,"remaining_time":0.3819670062},
{"learn":[0.02924595429],"iteration":762,"passed_time":1.223845145,"remaining_time":0.3801458709},
{"learn":[0.02917797749],"iteration":763,"passed_time":1.224784123,"remaining_time":0.3783364569},
{"learn":[0.02911710281],"iteration":764,"passed_time":1.226064989,"remaining_time":0.3766343431},
{"learn":[0.02904495368],"iteration":765,"passed_time":1.227930164,"remaining_time":0.3751118254},
{"learn":[0.02898378556],"iteration":766,"passed_time":1.228976909,"remaining_time":0.3733397913},
{"learn":[0.02893060675],"iteration":767,"passed_time":1.229911186,"remaining_time":0.3715356706},
{"learn":[0.0288547117],"iteration":768,"passed_time":1.230843788,"remaining_time":0.3697333096},
{"learn":[0.02877954336],"iteration":769,"passed_time":1.231982176,"remaining_time":0.3679946759},
{"learn":[0.02872751768],"iteration":770,"passed_time":1.233128438,"remaining_time":0.3662599382},
{"learn":[0.02868142953],"iteration":771,"passed_time":1.234210588,"remaining_time":0.3645077902},
{"learn":[0.02860770317],"iteration":772,"passed_time":1.235111809,"remaining_time":0.3627042441},
{"learn":[0.02855011592],"iteration":773,"passed_time":1.236164972,"remaining_time":0.3609473949},
{"learn":[0.02847537398],"iteration":774,"passed_time":1.237170492,"remaining_time":0.35917853},
{"learn":[0.02843326101],"iteration":775,"passed_time":1.238125084,"remaining_time":0.3573969313},
{"learn":[0.02836625622],"iteration":776,"passed_time":1.239978018,"remaining_time":0.355875287},
{"learn":[0.02831713053],"iteration":777,"passed_time":1.240888097,"remaining_time":0.35408375},
{"learn":[0.02827621882],"iteration":778,"passed_time":1.241952323,"remaining_time":0.3523382073},
{"learn":[0.02823700125],"iteration":779,"passed_time":1.242961059,"remaining_time":0.3505787604},
{"learn":[0.0281724563],"iteration":780,"passed_time":1.243977447,"remaining_time":0.3488233815},
{"learn":[0.02813625106],"iteration":781,"passed_time":1.245057276,"remaining_time":0.3470875782},
{"learn":[0.02807862942],"iteration":782,"passed_time":1.247220199,"remaining_time":0.3456536183},
{"learn":[0.02800832803],"iteration":783,"passed_time":1.248237785,"remaining_time":0.343902247},
{"learn":[0.02794372118],"iteration":784,"passed_time":1.249333522,"remaining_time":0.3421741492},
{"learn":[0.02790122766],"iteration":785,"passed_time":1.250254339,"remaining_time":0.3404000362},
{"learn":[0.02784225345],"iteration":786,"passed_time":1.251159851,"remaining_time":0.3386239494},
{"learn":[0.02777717205],"iteration":787,"passed_time":1.253361619,"remaining_time":0.3371988113},
{"learn":[0.02770654513],"iteration":788,"passed_time":1.254456488,"remaining_time":0.3354756894},
{"learn":[0.02763419885],"iteration":789,"passed_time":1.255397144,"remaining_time":0.333713165},
{"learn":[0.02758513964],"iteration":790,"passed_time":1.2565389,"remaining_time":0.3320058534},
{"learn":[0.02754313671],"iteration":791,"passed_time":1.257653647,"remaining_time":0.3302928769},
{"learn":[0.0274877915],"iteration":792,"passed_time":1.258676105,"remaining_time":0.3285573186},
{"learn":[0.02744320723],"iteration":793,"passed_time":1.260244752,"remaining_time":0.3269652631},
{"learn":[0.02738053982],"iteration":794,"passed_time":1.261619303,"remaining_time":0.3253232164},
{"learn":[0.02733009595],"iteration":795,"passed_time":1.262576411,"remaining_time":0.323574859},
{"learn":[0.02728512195],"iteration":796,"passed_time":1.263527264,"remaining_time":0.321826894},
{"learn":[0.02721504523],"iteration":797,"passed_time":1.26443323,"remaining_time":0.3200695645},
{"learn":[0.02715146083],"iteration":798,"passed_time":1.265430037,"remaining_time":0.3183372183},
{"learn":[0.02710440984],"iteration":799,"passed_time":1.266540555,"remaining_time":0.3166351388},
{"learn":[0.02706447014],"iteration":800,"passed_time":1.26799597,"remaining_time":0.3150202221},
{"learn":[0.02702002113],"iteration":801,"passed_time":1.268902312,"remaining_time":0.3132701468},
{"learn":[0.02696243387],"iteration":802,"passed_time":1.269828273,"remaining_time":0.311526986},
{"learn":[0.02691405095],"iteration":803,"passed_time":1.27098038,"remaining_time":0.3098409882},
{"learn":[0.02687877417],"iteration":804,"passed_time":1.272060796,"remaining_time":0.3081389506},
{"learn":[0.02682225292],"iteration":805,"passed_time":1.273575728,"remaining_time":0.3065430413},
{"learn":[0.02678206334],"iteration":806,"passed_time":1.274492557,"remaining_time":0.3048042919},
{"learn":[0.02671463902],"iteration":807,"passed_time":1.27602148,"remaining_time":0.303213025},
{"learn":[0.02665576797],"iteration":808,"passed_time":1.277050379,"remaining_time":0.3015038595},
{"learn":[0.0265997098],"iteration":809,"passed_time":1.2781515,"remaining_time":0.2998133147},
{"learn":[0.02654070121],"iteration":810,"passed_time":1.280145232,"remaining_time":0.2983322427},
{"learn":[0.02649490421],"iteration":811,"passed_time":1.281182562,"remaining_time":0.296628475},
{"learn":[0.02642144607],"iteration":812,"passed_time":1.282168509,"remaining_time":0.2949145279},
{"learn":[0.02638536233],"iteration":813,"passed_time":1.283132596,"remaining_time":0.2931973746},
{"learn":[0.02632448765],"iteration":814,"passed_time":1.284046428,"remaining_time":0.2914706616},
{"learn":[0.02626981644],"iteration":815,"passed_time":1.285846593,"remaining_time":0.2899458003},
{"learn":[0.02622539264],"iteration":816,"passed_time":1.287091552,"remaining_time":0.2882959045},
{"learn":[0.02617685153],"iteration":817,"passed_time":1.288071005,"remaining_time":0.2865879253},
{"learn":[0.02614626747],"iteration":818,"passed_time":1.288503794,"remaining_time":0.2847609117},
{"learn":[0.02610262999],"iteration":819,"passed_time":1.289490964,"remaining_time":0.2830589922},
{"learn":[0.02606822436],"iteration":820,"passed_time":1.290662745,"remaining_time":0.2813990637},
{"learn":[0.02600999062],"iteration":821,"passed_time":1.291677789,"remaining_time":0.2797063825},
{"learn":[0.02595872604],"iteration":822,"passed_time":1.293183969,"remaining_time":0.2781209751},
{"learn":[0.02591155584],"iteration":823,"passed_time":1.294235606,"remaining_time":0.276438673},
{"learn":[0.02585520653],"iteration":824,"passed_time":1.295139388,"remaining_time":0.2747265368},
{"learn":[0.02581937955],"iteration":825,"passed_time":1.296259119,"remaining_time":0.2730618483},
{"learn":[0.02576543505],"iteration":826,"passed_time":1.297339381,"remaining_time":0.2713902213},
{"learn":[0.02568858403],"iteration":827,"passed_time":1.298343328,"remaining_time":0.2697041696},
{"learn":[0.02564287644],"iteration":828,"passed_time":1.29954591,"remaining_time":0.2680607366},
{"learn":[0.02559077969],"iteration":829,"passed_time":1.301115593,"remaining_time":0.2664935552},
{"learn":[0.02555281841],"iteration":830,"passed_time":1.302107639,"remaining_time":0.2648088941},
{"learn":[0.02551524226],"iteration":831,"passed_time":1.303003838,"remaining_time":0.2631065442},
{"learn":[0.02546613033],"iteration":832,"passed_time":1.303908854,"remaining_time":0.2614078974},
{"learn":[0.02542432913],"iteration":833,"passed_time":1.304751492,"remaining_time":0.2596987382},
{"learn":[0.02537187246],"iteration":834,"passed_time":1.30574427,"remaining_time":0.2580213229},
{"learn":[0.02533383553],"iteration":835,"passed_time":1.30701861,"remaining_time":0.25640078},
{"learn":[0.02527517539],"iteration":836,"passed_time":1.308020419,"remaining_time":0.2547279907},
{"learn":[0.02522773009],"iteration":837,"passed_time":1.308993083,"remaining_time":0.2530511687},
{"learn":[0.02519329695],"iteration":838,"passed_time":1.309955753,"remaining_time":0.2513741076},
{"learn":[0.0251376285],"iteration":839,"passed_time":1.311071591,"remaining_time":0.249727922},
{"learn":[0.02509936461],"iteration":840,"passed_time":1.312252369,"remaining_time":0.2480952755},
{"learn":[0.02506069954],"iteration":841,"passed_time":1.316699166,"remaining_time":0.2470765656},
{"learn":[0.02502118624],"iteration":842,"passed_time":1.317719759,"remaining_time":0.2454116278},
{"learn":[0.02498204891],"iteration":843,"passed_time":1.318714581,"remaining_time":0.2437434533},
{"learn":[0.02493781768],"iteration":844,"passed_time":1.320123153,"remaining_time":0.2421527678},
{"learn":[0.02488577824],"iteration":845,"passed_time":1.321276356,"remaining_time":0.240516027},
{"learn":[0.02483646228],"iteration":846,"passed_time":1.322495113,"remaining_time":0.2388922695},
{"learn":[0.02480063989],"iteration":847,"passed_time":1.323495847,"remaining_time":0.2372303876},
{"learn":[0.02476895772],"iteration":848,"passed_time":1.324513464,"remaining_time":0.235573066},
{"learn":[0.02471961654],"iteration":849,"passed_time":1.325484626,"remaining_time":0.2339090517},
{"learn":[0.0246907037],"iteration":850,"passed_time":1.326589953,"remaining_time":0.2322701563},
{"learn":[0.0246402094],"iteration":851,"passed_time":1.32760477,"remaining_time":0.2306167911},
{"learn":[0.02460315594],"iteration":852,"passed_time":1.328613112,"remaining_time":0.2289638071},
{"learn":[0.02456035981],"iteration":853,"passed_time":1.329643887,"remaining_time":0.227316168},
{"learn":[0.02450676377],"iteration":854,"passed_time":1.330597939,"remaining_time":0.2256569604},
{"learn":[0.02447814208],"iteration":855,"passed_time":1.331834964,"remaining_time":0.2240470033},
{"learn":[0.02443684981],"iteration":856,"passed_time":1.333331209,"remaining_time":0.2224811702},
{"learn":[0.02438760721],"iteration":857,"passed_time":1.334988892,"remaining_time":0.2209422175},
{"learn":[0.02434192025],"iteration":858,"passed_time":1.336774921,"remaining_time":0.2194240557},
{"learn":[0.02429673076],"iteration":859,"passed_time":1.337825061,"remaining_time":0.217785475},
{"learn":[0.0242493657],"iteration":860,"passed_time":1.341131425,"remaining_time":0.2165125064},
{"learn":[0.02420703035],"iteration":861,"passed_time":1.342558909,"remaining_time":0.2149340248},
{"learn":[0.02417383286],"iteration":862,"passed_time":1.343536996,"remaining_time":0.2132845521},
{"learn":[0.02413755655],"iteration":863,"passed_time":1.344516364,"remaining_time":0.211636835},
{"learn":[0.02410512246],"iteration":864,"passed_time":1.345413762,"remaining_time":0.2099778703},
{"learn":[0.02405920395],"iteration":865,"passed_time":1.34656548,"remaining_time":0.2083600166},
{"learn":[0.02401909003],"iteration":866,"passed_time":1.347684397,"remaining_time":0.2067382063},
{"learn":[0.02397829294],"iteration":867,"passed_time":1.348660854,"remaining_time":0.2050958902},
{"learn":[0.02392858725],"iteration":868,"passed_time":1.350543104,"remaining_time":0.2035916532},
{"learn":[0.02388878052],"iteration":869,"passed_time":1.352608185,"remaining_time":0.2021138668},
{"learn":[0.02385135339],"iteration":870,"passed_time":1.354056617,"remaining_time":0.2005434024},
{"learn":[0.02382420577],"iteration":871,"passed_time":1.3551423,"remaining_time":0.1989199707},
{"learn":[0.02378344307],"iteration":872,"passed_time":1.356280879,"remaining_time":0.1973054658},
{"learn":[0.02372780442],"iteration":873,"passed_time":1.357779574,"remaining_time":0.195743966},
{"learn":[0.02369108108],"iteration":874,"passed_time":1.358712947,"remaining_time":0.1941018495},
{"learn":[0.02365204921],"iteration":875,"passed_time":1.359868225,"remaining_time":0.1924927625},
{"learn":[0.02362415653],"iteration":876,"passed_time":1.360734324,"remaining_time":0.1908441526},
{"learn":[0.02358515904],"iteration":877,"passed_time":1.361710357,"remaining_time":0.1892126009},
{"learn":[0.02355280289],"iteration":878,"passed_time":1.362619882,"remaining_time":0.1875733853},
{"learn":[0.02351841101],"iteration":879,"passed_time":1.363556448,"remaining_time":0.1859395157},
{"learn":[0.02347230453],"iteration":880,"passed_time":1.364468982,"remaining_time":0.1843039828},
{"learn":[0.02344374932],"iteration":881,"passed_time":1.365375143,"remaining_time":0.1826692368},
{"learn":[0.02339728291],"iteration":882,"passed_time":1.367168253,"remaining_time":0.1811536644},
{"learn":[0.02336339309],"iteration":883,"passed_time":1.368347091,"remaining_time":0.1795568581},
{"learn":[0.02332520943],"iteration":884,"passed_time":1.369479298,"remaining_time":0.177954937},
{"learn":[0.02325315659],"iteration":885,"passed_time":1.370531683,"remaining_time":0.1763438057},
{"learn":[0.02322585766],"iteration":886,"passed_time":1.37189238,"remaining_time":0.1747732119},
{"learn":[0.02318479923],"iteration":887,"passed_time":1.37324861,"remaining_time":0.1732025273},
{"learn":[0.02315599643],"iteration":888,"passed_time":1.376527359,"remaining_time":0.1718723699},
{"learn":[0.02311678116],"iteration":889,"passed_time":1.377539393,"remaining_time":0.1702576778},
{"learn":[0.02307898723],"iteration":890,"passed_time":1.378570551,"remaining_time":0.168646678},
{"learn":[0.02304459535],"iteration":891,"passed_time":1.379645719,"remaining_time":0.1670423068},
{"learn":[0.02300538237],"iteration":892,"passed_time":1.38380459,"remaining_time":0.1658086127},
{"learn":[0.02294579836],"iteration":893,"passed_time":1.384814571,"remaining_time":0.1641950163},
{"learn":[0.02291816702],"iteration":894,"passed_time":1.386160831,"remaining_time":0.1626222204},
{"learn":[0.02288452708],"iteration":895,"passed_time":1.387563102,"remaining_time":0.1610564315},
{"learn":[0.02285969257],"iteration":896,"passed_time":1.388545619,"remaining_time":0.159442808},
{"learn":[0.02282725389],"iteration":897,"passed_time":1.389589621,"remaining_time":0.1578375739},
{"learn":[0.02278703451],"iteration":898,"passed_time":1.390740811,"remaining_time":0.1562456306},
{"learn":[0.02275233315],"iteration":899,"passed_time":1.391795415,"remaining_time":0.154643935},
{"learn":[0.02272798465],"iteration":900,"passed_time":1.393589179,"remaining_time":0.1531246711},
{"learn":[0.02268751768],"iteration":901,"passed_time":1.394636392,"remaining_time":0.1515236878},
{"learn":[0.02266100508],"iteration":902,"passed_time":1.395628354,"remaining_time":0.1499179959},
{"learn":[0.02261574222],"iteration":903,"passed_time":1.397047454,"remaining_time":0.1483590217},
{"learn":[0.02259093523],"iteration":904,"passed_time":1.400722159,"remaining_time":0.1470371327},
{"learn":[0.02255254067],"iteration":905,"passed_time":1.401989694,"remaining_time":0.1454602994},
{"learn":[0.02251787828],"iteration":906,"passed_time":1.40331264,"remaining_time":0.1438898297},
{"learn":[0.0224854992],"iteration":907,"passed_time":1.404383901,"remaining_time":0.1422944041},
{"learn":[0.02245056171],"iteration":908,"passed_time":1.406400241,"remaining_time":0.1407947436},
{"learn":[0.02241092003],"iteration":909,"passed_time":1.407445234,"remaining_time":0.1391978803},
{"learn":[0.02237772712],"iteration":910,"passed_time":1.40845062,"remaining_time":0.1375983591},
{"learn":[0.02234825721],"iteration":911,"passed_time":1.409499162,"remaining_time":0.1360043051},
{"learn":[0.02231003],"iteration":912,"passed_time":1.410462664,"remaining_time":0.1344033426},
{"learn":[0.02227465923],"iteration":913,"passed_time":1.411573857,"remaining_time":0.1328176714},
{"learn":[0.02223479289],"iteration":914,"passed_time":1.412846489,"remaining_time":0.1312480345},
{"learn":[0.02219149929],"iteration":915,"passed_time":1.414219988,"remaining_time":0.1296882959},
{"learn":[0.02215637611],"iteration":916,"passed_time":1.415386734,"remaining_time":0.1281102497},
{"learn":[0.02212806848],"iteration":917,"passed_time":1.416414079,"remaining_time":0.1265206475},
{"learn":[0.02208691377],"iteration":918,"passed_time":1.417426737,"remaining_time":0.1249309746},
{"learn":[0.02205378505],"iteration":919,"passed_time":1.418490529,"remaining_time":0.1233470026},
{"learn":[0.0220240836],"iteration":920,"passed_time":1.419953154,"remaining_time":0.1217983704},
{"learn":[0.02199821289],"iteration":921,"passed_time":1.421062121,"remaining_time":0.1202200059},
{"learn":[0.02196578796],"iteration":922,"passed_time":1.422134789,"remaining_time":0.1186396303},
{"learn":[0.02193012834],"iteration":923,"passed_time":1.423264102,"remaining_time":0.1170650127},
{"learn":[0.02190206372],"iteration":924,"passed_time":1.424279504,"remaining_time":0.1154821219},
{"learn":[0.02186908401],"iteration":925,"passed_time":1.425197687,"remaining_time":0.1138926877},
{"learn":[0.02182479776],"iteration":926,"passed_time":1.426995055,"remaining_time":0.1123739363},
{"learn":[0.02179642824],"iteration":927,"passed_time":1.427944474,"remaining_time":0.1107887954},
{"learn":[0.02175827668],"iteration":928,"passed_time":1.429030698,"remaining_time":0.1092154785},
{"learn":[0.02173835956],"iteration":929,"passed_time":1.43007883,"remaining_time":0.107640342},
{"learn":[0.02170942609],"iteration":930,"passed_time":1.431038025,"remaining_time":0.1060597462},
{"learn":[0.02168088693],"iteration":931,"passed_time":1.43195702,"remaining_time":0.1044775508},
{"learn":[0.02165016303],"iteration":932,"passed_time":1.433661346,"remaining_time":0.1029531728},
{"learn":[0.02162989057],"iteration":933,"passed_time":1.435466689,"remaining_time":0.1014355476},
{"learn":[0.02160366453],"iteration":934,"passed_time":1.436521386,"remaining_time":0.09986512307},
{"learn":[0.0215687981],"iteration":935,"passed_time":1.437760763,"remaining_time":0.09830842826},
{"learn":[0.02152140324],"iteration":936,"passed_time":1.438719339,"remaining_time":0.09673353077},
{"learn":[0.02150229995],"iteration":937,"passed_time":1.439837256,"remaining_time":0.09517047958},
{"learn":[0.02146371053],"iteration":938,"passed_time":1.440928496,"remaining_time":0.09360664353},
{"learn":[0.02141822989],"iteration":939,"passed_time":1.442443898,"remaining_time":0.09207088714},
{"learn":[0.02138902362],"iteration":940,"passed_time":1.443393634,"remaining_time":0.09049970716},
{"learn":[0.02135104399],"iteration":941,"passed_time":1.444396999,"remaining_time":0.08893314858},
{"learn":[0.02132749099],"iteration":942,"passed_time":1.445386088,"remaining_time":0.08736692155},
{"learn":[0.02130352075],"iteration":943,"passed_time":1.446562164,"remaining_time":0.08581300971},
{"learn":[0.02126883314],"iteration":944,"passed_time":1.44760458,"remaining_time":0.08425211841},
{"learn":[0.02124211421],"iteration":945,"passed_time":1.44857677,"remaining_time":0.08268831456},
{"learn":[0.0212138341],"iteration":946,"passed_time":1.449738162,"remaining_time":0.08113634909},
{"learn":[0.02118765849],"iteration":947,"passed_time":1.450983358,"remaining_time":0.07958980447},
{"learn":[0.02116369284],"iteration":948,"passed_time":1.452011533,"remaining_time":0.07803223201},
{"learn":[0.02113257463],"iteration":949,"passed_time":1.453191944,"remaining_time":0.07648378653},
{"learn":[0.02110002591],"iteration":950,"passed_time":1.454366797,"remaining_time":0.07493582863},
{"learn":[0.0210562761],"iteration":951,"passed_time":1.455908506,"remaining_time":0.07340715158},
{"learn":[0.02102742287],"iteration":952,"passed_time":1.456962497,"remaining_time":0.07185439389},
{"learn":[0.02099923446],"iteration":953,"passed_time":1.457911304,"remaining_time":0.07029761005},
{"learn":[0.02097067466],"iteration":954,"passed_time":1.458876065,"remaining_time":0.06874285121},
{"learn":[0.02094150048],"iteration":955,"passed_time":1.459917261,"remaining_time":0.06719284467},
{"learn":[0.0209157421],"iteration":956,"passed_time":1.461341913,"remaining_time":0.06566113087},
{"learn":[0.02086107547],"iteration":957,"passed_time":1.462962828,"remaining_time":0.06413824507},
{"learn":[0.0208150561],"iteration":958,"passed_time":1.463973664,"remaining_time":0.06258907217},
{"learn":[0.02078169126],"iteration":959,"passed_time":1.464975207,"remaining_time":0.06104063363},
{"learn":[0.02074706784],"iteration":960,"passed_time":1.466134231,"remaining_time":0.05949972426},
{"learn":[0.02070328593],"iteration":961,"passed_time":1.467186077,"remaining_time":0.0579553752},
{"learn":[0.02067771783],"iteration":962,"passed_time":1.468312012,"remaining_time":0.05641489557},
{"learn":[0.02063510739],"iteration":963,"passed_time":1.469329748,"remaining_time":0.05487123542},
{"learn":[0.02059206367],"iteration":964,"passed_time":1.471250801,"remaining_time":0.05336142801},
{"learn":[0.02056032648],"iteration":965,"passed_time":1.473299984,"remaining_time":0.05185527894},
{"learn":[0.02052464393],"iteration":966,"passed_time":1.474302801,"remaining_time":0.05031229826},
{"learn":[0.02050409638],"iteration":967,"passed_time":1.476011364,"remaining_time":0.04879376409},
{"learn":[0.02048401878],"iteration":968,"passed_time":1.477578677,"remaining_time":0.04727031889},
{"learn":[0.02045800136],"iteration":969,"passed_time":1.4785513,"remaining_time":0.04572839071},
{"learn":[0.02042597532],"iteration":970,"passed_time":1.479760608,"remaining_time":0.04419470406},
{"learn":[0.0203911983],"iteration":971,"passed_time":1.480744425,"remaining_time":0.04265518919},
{"learn":[0.02034819355],"iteration":972,"passed_time":1.481723872,"remaining_time":0.04111669532},
{"learn":[0.02031286405],"iteration":973,"passed_time":1.483234071,"remaining_time":0.0395935173},
{"learn":[0.02028087469],"iteration":974,"passed_time":1.48473882,"remaining_time":0.03807022615},
{"learn":[0.02025393569],"iteration":975,"passed_time":1.486356395,"remaining_time":0.03654974742},
{"learn":[0.02022101329],"iteration":976,"passed_time":1.487505623,"remaining_time":0.03501804436},
{"learn":[0.02018768054],"iteration":977,"passed_time":1.488583826,"remaining_time":0.03348552575},
{"learn":[0.02015766501],"iteration":978,"passed_time":1.490216185,"remaining_time":0.03196582215},
{"learn":[0.02013157881],"iteration":979,"passed_time":1.491207111,"remaining_time":0.03043279818},
{"learn":[0.0201048553],"iteration":980,"passed_time":1.492685575,"remaining_time":0.02891032204},
{"learn":[0.02007846649],"iteration":981,"passed_time":1.493822806,"remaining_time":0.02738168076},
{"learn":[0.02004561745],"iteration":982,"passed_time":1.494794265,"remaining_time":0.02585096897},
{"learn":[0.02000636779],"iteration":983,"passed_time":1.495805785,"remaining_time":0.02432204528},
{"learn":[0.01998394728],"iteration":984,"passed_time":1.496883863,"remaining_time":0.02279518574},
{"learn":[0.0199552591],"iteration":985,"passed_time":1.497866503,"remaining_time":0.02126788138},
{"learn":[0.01993200183],"iteration":986,"passed_time":1.498825688,"remaining_time":0.01974137178},
{"learn":[0.01990113121],"iteration":987,"passed_time":1.50010437,"remaining_time":0.01821989114},
{"learn":[0.01988117053],"iteration":988,"passed_time":1.50127715,"remaining_time":0.01669772361},
{"learn":[0.01986589569],"iteration":989,"passed_time":1.50230894,"remaining_time":0.01517483777},
{"learn":[0.01983512823],"iteration":990,"passed_time":1.504240647,"remaining_time":0.01366111586},
{"learn":[0.01980050252],"iteration":991,"passed_time":1.505289924,"remaining_time":0.01213943487},
{"learn":[0.0197628897],"iteration":992,"passed_time":1.506590317,"remaining_time":0.01062047555},
{"learn":[0.01973701211],"iteration":993,"passed_time":1.507576702,"remaining_time":0.009100060573},
{"learn":[0.01970943121],"iteration":994,"passed_time":1.508490933,"remaining_time":0.007580356448},
{"learn":[0.01968132991],"iteration":995,"passed_time":1.509522994,"remaining_time":0.00606234134},
{"learn":[0.01965290996],"iteration":996,"passed_time":1.510378354,"remaining_time":0.004544769369},
{"learn":[0.01961723199],"iteration":997,"passed_time":1.511581413,"remaining_time":0.003029221269},
{"learn":[0.01958551544],"iteration":998,"passed_time":1.513247423,"remaining_time":0.001514762185},
{"learn":[0.01954740515],"iteration":999,"passed_time":1.514258585,"remaining_time":0}
]}